Workbook

Sheet survey
A1: ID | B1: Start time | C1: Completion time | D1: Email | E1: Name | F1: Last modified time | G1: Your full name (Firstname Lastname): | H1: Your email address (will be used only if follow-up clarifications would be needed): | I1: Your organization: | J1: For the model/scenarios of which work package (WP), are you filling out this survey? | K1: The name of the modeling tool for which you fill out the survey: | L1: What is the main category of the model? | M1: What option describes your modeling approach best? | N1: What geographical scope presents your model best? | O1: What is the spatial resolution of your model concerning the EU region? | P1: What level(s) of the electricity network is represented in your model? | Q1: How are cross-border transmission lines between EU countries represented in your model? | R1: How the planning foresight is treated in your model: | S1: What time intervals are considered in the model horizon? (Please tick all that apply) | T1: What planning/modeling horizon is used in your analysis? | U1: How is the sub-annual temporal resolution represented in your model? | V1: If you answered "Representative time slices" or "Other", please explain. For example, the method of sampling/clustering and/or the length of time slices. | W1: Is the chronology of (sub-annual) time slices preserved in your modeling work? | X1: Is the joint variability of supply and demand resources in each sub-annual time slice captured in your model? This means, e.g., the timeseries of wind, solar PV, and demand are all concurrent with... | Y1: How are short-term operational events represented in your model? Short-term decisions are in the scale of hours to a few days including generator scheduling, ramping rates, flexibility requirement... | Z1: If short-term decisions are not represented explicitly in your model, how is the relevant parametrization done? Check all relevant answers. | AA1: How are short-term decisions linked to long-term infrastructure planning and investment decisions in your model? Long-term decisions refer to multi-decadal decisions such as investment in power pl... | AB1: Is the weather uncertainty in multiple years included in your model parameters? | AC1: What future uncertainties are considered when representing sub-annual temporal variability in your model parameters? Here, we refer to those events not driven by socioeconomic developments or cost... | AD1: What is the level of granularity in representing technologies in your model? | AE1: Which of the following demand and supply-side sectors are included in your model? Please choose all that apply. | AF1: How electricity demand is represented in your model? | AG1: If your answer was "Other", please explain: | AH1: Which VRE sources are represented in your model? Please choose all that apply. | AI1: What aspect(s) of VRE is represented in the model? Please choose all that apply. | AJ1: What VRE integration costs or requirements are modeled explicitly, i.e., depending on the capacity/generation of VRE? Please choose all that apply. | AK1: Please explain the representation of VRE integration in your model, if it cannot be described by the options above or in case of ticking "Other". | AL1: Can load be technically met only by VRE in a given (sub-annual) time slice in your model? | AM1: What constraints limit the penetration of VRE in your model? Please choose all that apply. | AN1: Please explain any additional points considering the constraints in your model that would limit the penetration of VRE, e.g., to meet 100% of the load. | AO1: How the mismatch between electricity from VRE and load can be balanced in your model? Please choose all that apply. | AP1: Have you explicitly modeled one or several electricity storage technologies in your model? | AQ1: What forms of storage duration are considered in your model? The storage duration can be attributed to the choice of technology, e.g., batteries for the short and pumped hydro for the long term. P... | AR1: What storage technology categories are represented in your model? Please choose all that apply. | AS1: Do you represent various storage technologies within a category (e.g., different battery chemistries) in your model? | AT1: Please list technologies represented within each category mentioned above, only for applicable categories (e.g., Batteries: Li-ion, Lead-acid). | AU1: What technical characteristics of electricity storage are modeled explicitly? Please choose all that apply. | AV1: If applicable, please list other characteristics of storage represented in your model that are not listed above: | AW1: What economic characteristics of electricity storage are modeled explicitly? (O&M = operation and maintenance). Please choose all that apply. | AX1: Are the costs of the power conversion system (PCS) and the storage reservoir/container represented separately in your model? | AY1: Which service categories are relevant for storage technologies in your model? Please tick all that apply. | AZ1: Where are storage technologies represented in your model? Please tick all that apply. | BA1: Which energy-related storage services are represented in your model? Please tick all that apply. | BB1: Which power capacity-related storage services are represented in your model? Please tick all that apply. | BC1: Which T&D-related storage services are represented in your model? Please tick all that apply. | BD1: Which storage services concerning VRE are represented in your model? Please tick all that apply. | BE1: Please briefly explain the way energy storage can support the integration of VRE in your model, if not fully covered through the questions asked above. | BF1: Which one of the following parameters affects the deployment of energy storage technologies in your model positively? Please tick all that apply. | BG1: Please explain if the answer included "Other" and/or if you would like to add explanations. | BH1: How is the system integration of electricity storage constrained in your model? Please tick all that apply. | BI1: Can storage technologies contribute to multiple services in your model? This functionality known as "revenue stacking" or "aggregation of benefits" allows a storage provider to offer energy-, cap... | BJ1: How is the ownership of storage and its revenues represented in your model? | BK1: Please add any points related to the integration of energy storage in your model that you believe are not covered in the previous questions. | BL1: Are energy storage technologies and their parameters treated differently based on the modeled scenario in your work? (e.g., more optimistic energy storage cost assumptions in electrification scena... | BM1: If relevant, please explain your scenario-specific assumptions concerning storage technologies briefly. For example, do you consider different storage performance/cost parameters or storage integr... | BN1: (Only for the teams in the ECEMF project) We need additional variables for conducting the storage analysis. Please tick all Priority 1 variables that you can report for your scenarios.
A2: 2 | B2: 45552.525 | C2: 45552.537 | D2: anonymous | G2: Panagiotis Fragkos | H2: panagiotis.fragkos@ricardo.com | I2: E3Modelling | J2: WP1 (Task 1.3); | K2: PROMETHEUS | L2: Integrated assessment model | M2: Market simulation | N2: Global | O2: EU divided in 2-3 subregions | P2: Coarse copperplate (multiple countries in one modeling node) | Q2: Not modeled | R2: Myopic foresight (short sighted) | S2: Yearly; | T2: ~2050 (mid century) | U2: Yearly (No sub-annual time slices) | Y2: Short-term events are represented implicitly, e.g., as a cost or other proxy. | Z2: Using data from various empirical or model-based studies; | AA2: Short-term decisions are represented using proxies and/or in a stylized format as part of long-term decisionmaking | AB2: Yes, using varying input data (or sensitivity analysis) | AC2: Climate impact on the supply side;Climate impact on the demand side; | AD2: Technologies by input fuel type (e.g., all gas power plant types aggregated together) | AE2: Buildings;Fossil fuel supply ;Industry sector;Renewable-based fuels and derivatives (e.g., green hydrogen);Power (supply) sector;Transport sector; | AF2: Demand is modeled endogenously | AH2: Concentrated solar power (CSP) (w/o storage);Onshore wind;Offshore wind;Solar photovoltaic (PV) (general); | AI2: Direct costs (capital, O&M, etc.);Indirect costs (integration costs);Resource potential;Technical characteristics (efficiency, capacity factor, etc.) ;Weather dependency (varying output in different time scales within a year); | AJ2: Grid management/contingency costs;Additional ancillary/balancing services costs (economic);Reduced capacity factor of non-VRE; | AL2: Yes (but partly has to be with stored or firmed VRE) | AM2: Integration cost (economic/implicit);Resource potential;Maximum share of VRE (either from generation, load, input to T&D, etc.); | AO2: Electricity storage;Power to hydrogen (electrolyzers); | AP2: Yes | AQ2: Short-term (hours to a few days);Long-term (months to seasons); | AR2: Storage is represented as a generic or homogenous asset w/o specific technology types.; | AS2: No | AU2: Capacity factor (max or nominal);Charge capacity (MW) (if it can be different from discharge capacity);Lifetime (in years);Power capacity (MW) (used for both charge and discharge); | AW2: Capital cost;Variable O&M cost;Fixed O&M cost;End-of-lifetime cost or resale; | AX2: No (PCS and reservoir are treated with one cost value) | AY2: Renewable energy integration (e.g., curtailment reduction);Energy-related (e.g., peak shaving); | AZ2: Storage is represented generically (no location specific); | BA2: Energy-related services are modeled collectively.; | BB2: Capacity-related services are modeled collectively.; | BC2: Not relevant; | BD2: Curtailment reduction;Energy time-shifting; | BF2: Cost competetiveness (incl. capital cost, O&M cost, levelized cost, etc.) compared to other alternatives;Rapid cost learning, i.e., the decline of storage cost in future;The increasing share of VRE in the system (e.g., as % of annual load or generation);The value of capacity services of storage;Increased variability in the pattern of VRE within a year; | BH2: Storage capacity/activity is dependent to that of VRE (i.e., no VRE --> no storage).; | BI2: Not relevant | BJ2: Not relevant | BL2: Yes | BM2: yes | BN2: Capacity of storage (GWh);Capital cost of storage technologies (EUR/GW or EUR/GWh);
A3: 3 | B3: 45552.552 | C3: 45552.637 | D3: anonymous | G3: Harmen Sytze de Boer | H3: boerdhs@pbl.nl | I3: PBL | J3: WP1 (Task 1.3);WP3;WP5; | K3: IMAGE | L3: Integrated assessment model | M3: Investment and capacity exapnsion planning | N3: Global | O3: EU divided in 2-3 subregions | P3: Coarse copperplate (multiple countries in one modeling node) | Q3: Using proxies or stylized methods | R3: Recursive dynamic (feedback loop) | S3: Yearly; | T3: ~2100 (full century) | U3: Multi-hourly | W3: No | X3: Yes, although the demand pattern is historic and not based on endogenous demand sector developments | Y3: A few extreme short-term events are represented explicitly (e.g., seasonal peak load and zero supply from renewables). | Z3: Using data from various empirical or model-based studies;We use the RLDC dataset developed by PIK during the ADVANCE project (Ueckerdt et al., 2016); | AA3: Short-term decisions are represented using proxies and/or in a stylized format as part of long-term decisionmaking | AB3: Data of one representative year based on irradiation and wind speed data for 1984–2005 | AC3: None of the above or not relevant; | AD3: Scale-free technology types (e.g., different gas power plant types aggregated separately) | AE3: Buildings;Fossil fuel supply ;Heat supply (including district heating/cooling);Industry sector;Renewable-based fuels and derivatives (e.g., green hydrogen);Power (supply) sector;Transport sector; | AF3: Depends on the sector. Some are modelled in much detail (transport, industry), while other are more aggregated | AG3: Depends on the sector. Some are modelled in much detail (transport, industry), while other are more aggregated | AH3: Concentrated solar power (CSP) (w/o storage);Onshore wind;Offshore wind;Run-of-the-river hydropower (w/o storage);Solar photovoltaic (PV) (general);Solar photovoltaic (PV) (rooftop);Solar photovoltaic (PV) (utility);Tidal or marine energy; | AI3: Capacity value (contribution to power adequacy);Curtailment;Direct costs (capital, O&M, etc.);Indirect costs (integration costs);Resource potential;Technical characteristics (efficiency, capacity factor, etc.) ;Weather dependency (varying output in different time scales within a year); | AJ3: Curtailment cost (i.e., cost of handling excess electricity or negative prices);Grid expansion or fortification needs;Reduced capacity factor of non-VRE;Storage requirements for energy time-shifting; | AL3: Yes (no need for generation from non-VRE or discharge from storage) | AM3: Integration requirements (technical/explicit, e.g., grid expansion and/or storage scale-up);Resource potential;Integration cost (economic/implicit); | AN3: At some point, the load factor of any marginal solar/wind capacity gets quite small due to curtailments. Also, VRE can be backup for VRE. However, the firm capacity of marginal solar/wind capacity also gets quite low (increasing backup costs) | AO3: Curtailment of VRE;Electricity storage;Flexible electricity generation from thermal power (e.g., biomass, coal, gas) with or w/o CCS;Flexible electricity generation from hydropower;Flexible electricity generation from nuclear power;Power to hydrogen (electrolyzers); | AP3: No, storage is modeled as cost or other proxy | AQ3: Short-term (hours to a few days);Medium-term (a few weeks);Long-term (months to seasons); | AR3: Flow batteries (e.g., Vanadium-Redox);Storage in the form of hydrogen; | AS3: No | AU3: Our flow battery storage is included in the RLDC dataset we use. For certain shares of wind/solar, the dataset provides us with required storage capacity (MW/MWh). Round trip efficiencies are included in the dataset. Hydrogen can also be used as a way of storing electricity (although the hydrogen is not necessarily used again in het electricity sector); | AW3: Capital cost; | AX3: No (PCS and reservoir are treated with one cost value) | AY3: Renewable energy integration (e.g., curtailment reduction);Power capacity-related (e.g., capacity firming);Energy-related (e.g., peak shaving); | AZ3: At the generation side (utility VRE);At the generation side (central power plants); | BA3: Peak shaving (e.g., daily, seasonal); | BB3: Capacity firming of non-VRE (e.g., day/night smoothing of nuclear power); | BC3: Grid services are modeled collectively.; | BD3: Curtailment reduction;Capacity firming (increasing capacity value of VRE); | BF3: The increasing share of VRE in the system (e.g., as % of annual load or generation); | BH3: The RLDC dataset we use includes required storage capacity for different shares of VRE; | BI3: No, the contribution of storage is only allowed to certain services (e.g., either to energy- or capacity-related services). | BJ3: Storage contributes to the system-level benefits. | BL3: Yes | BM3: The RLDC dataset (including storage) is available for various levels of VRE integration constraints (strict, normal, relaxed) | BN3: Capacity of storage (GWh);Electricity supplied/discharged by storage technologies (EJ/yr);Power capacity of electricity storage (GW);Power capacity of hydrogen electrolyzer (GW);
A4: 5 | B4: 45558.575 | C4: 45558.621 | D4: anonymous | G4: Igor Tatarewicz | H4: igor.tatarewicz@kobize.pl | I4: KOBIZE/CAKE | J4: WP1 (Task 1.3);WP5; | K4: MEESA | L4: Power system model | M4: Investment and capacity exapnsion planning | N4: Europe (e.g., EU27 & UK & EEA) | O4: Multiple-country (~1-4 EU countries in each model region) | P4: Coarse copperplate (multiple countries in one modeling node) | Q4: Using a backbone or star model (nodes connected via a central grid) | R4: Perfect foresight | S4: 2- to 5-yearly; | T4: ~2050 (mid century) | U4: Representative time slices (sampled or clustered) | V4: 18 or 72 time slices - two seasons, 3 types of day per season, 3 day periods - (day, night, peak in 18 TS) or 12 2-hours periods per day (in 72 TS) | W4: Yes | X4: Yes, for all time slices | Y4: A few extreme short-term events are represented explicitly (e.g., seasonal peak load and zero supply from renewables). | Z4: Using data from various empirical or model-based studies; | AA4: Short- and long-term decisions are co-optimized in an integrated way. | AB4: Yes, using varying input data (or sensitivity analysis) | AC4: Operational uncertainty (e.g., generator outages or demand or renewable energy forecast errors); | AD4: Technologies by input fuel type (e.g., all gas power plant types aggregated together) | AE4: Fossil fuel supply ;Heat supply (including district heating/cooling);Renewable-based fuels and derivatives (e.g., green hydrogen);Power (supply) sector; | AF4: Static demand (no response to supply cost) | AH4: Onshore wind;Offshore wind;Run-of-the-river hydropower (w/o storage);Solar photovoltaic (PV) (rooftop);Solar photovoltaic (PV) (utility); | AI4: Capacity value (contribution to power adequacy);Direct costs (capital, O&M, etc.);Technical characteristics (efficiency, capacity factor, etc.) ;Weather dependency (varying output in different time scales within a year);Resource potential; | AJ4: Additional ancillary/balancing services costs (economic); | AK4: increasing variable VRE cost as the use of a given technology increases, simulating additional network/balancing costs | AL4: Yes (no need for generation from non-VRE or discharge from storage) | AM4: Resource potential;Minimum share of non-VRE technologies (e.g., stabilizing share, firm capacity, etc.);Integration requirements (technical/explicit, e.g., grid expansion and/or storage scale-up);Temporal or spatial mismatch between VRE and load; | AO4: Electricity storage;Flexible electricity generation from thermal power (e.g., biomass, coal, gas) with or w/o CCS;Flexible electricity generation from nuclear power;Power to hydrogen (electrolyzers);Demand response in transport (e.g., smart charging of EVs);Demand response (generic, no sector-specific);Curtailment of VRE;Curtailment of load (unserved energy);Electricity export/import (grid connection);Power to heat (w/ or w/o storage); | AP4: Yes | AQ4: Short-term (hours to a few days);Medium-term (a few weeks); | AR4: Pumped hydro storage;Secondary electorchemical batteries (e.g., Li-ion, etc.);hydrogen storage; | AS4: No | AU4: Lifetime (in years);Power capacity (MW) (used for both charge and discharge);Storage content balance (equal storage content at the beginning and end of a model year/period);Duration of discharge or energy-to-power ratio (h);Charge capacity (MW) (if it can be different from discharge capacity);Discharging efficiency;Discharge capacity (MW) (if it can be different from charge capacity);Charging efficiency; | AW4: Capital cost;Variable O&M cost;Fixed O&M cost; | AX4: Yes (for some or all technologies) | AY4: Energy-related (e.g., peak shaving);Power capacity-related (e.g., capacity firming);Renewable energy integration (e.g., curtailment reduction); | AZ4: Power transmission level;Power distribution level;End-use side (buildings); | BA4: Peak shaving (e.g., daily, seasonal);Energy time shifting (arbitrage);Increasing self-consumption at the end use side; | BB4: Capacity-related services are modeled collectively.; | BC4: Transmission and distribution services are represented separately.; | BD4: VRE-related services of storage are modeled in an aggregated way (i.e., no individual representation of services).; | BF4: Cost competetiveness (incl. capital cost, O&M cost, levelized cost, etc.) compared to other alternatives;Rapid cost learning, i.e., the decline of storage cost in future;The increasing share of VRE in the system (e.g., as % of annual load or generation);Increased volatility in the pattern of electric load within a year;Increased variability in the pattern of VRE within a year; | BH4: Storage is constrained by build-up, technological learning, and/or market-penetration growth rates (i.e., dynamic constraints dependent on storage deployment).;(Some or all) storage technologies are constrained by available sites, resource potential, material availability, etc. (i.e., static constraints not necessarily dependent on storage deployment); | BI4: No, the contribution of storage is only allowed to certain services (e.g., either to energy- or capacity-related services). | BJ4: Storage contributes to the system-level benefits. | BL4: No, storage parameters were kept consistently across scenarios. | BM4: - | BN4: Capacity of storage (GWh);Capital cost of storage technologies (EUR/GW or EUR/GWh);Duration of charge/discharge (h);Efficiency of storage technologies (as % or lost energy (EJ/yr));Electricity supplied/discharged by storage technologies (EJ/yr);Lifetime of storage technologies (year);Net electricity trade (import/export) (EJ/yr);Power capacity of electricity storage (GW);Power capacity of hydrogen electrolyzer (GW);
A5: 7 | B5: 45561.504 | C5: 45561.509 | D5: anonymous | G5: Johannes Emmerling | H5: johannes.emmerling@cmcc.it | I5: CMCC | J5: WP3;WP5;WP1 (Task 1.3); | K5: WITCH | L5: Integrated assessment model | M5: Macro-economic modeling | N5: Global | O5: EU- or European level (one model region) | P5: Coarse copperplate (multiple countries in one modeling node) | Q5: Not modeled | R5: Perfect foresight | S5: 2- to 5-yearly; | T5: ~2100 (full century) | U5: Yearly (No sub-annual time slices) | Y5: Short-term events are represented implicitly, e.g., as a cost or other proxy. | Z5: Using data from various empirical or model-based studies; | AA5: Short-term decisions are not relevant to the modeling scope. | AB5: No | AC5: Climate impact on the supply side;Climate impact on the demand side; | AD5: Technologies by input fuel type (e.g., all gas power plant types aggregated together) | AE5: Buildings;Power (supply) sector;Transport sector; | AF5: Static demand (no response to supply cost) | AH5: Concentrated solar power (CSP) (w/o storage);Onshore wind;Offshore wind;Solar photovoltaic (PV) (general); | AI5: Capacity value (contribution to power adequacy);Curtailment;Direct costs (capital, O&M, etc.);Indirect costs (integration costs);Resource potential; | AJ5: Curtailment cost (i.e., cost of handling excess electricity or negative prices);Grid expansion or fortification needs; | AL5: No (there must be a level of non-VRE generation) | AM5: Maximum share of VRE (either from generation, load, input to T&D, etc.); | AO5: Curtailment of VRE;Electricity storage; | AP5: No, storage is modeled as cost or other proxy | AQ5: Long-term (months to seasons);Medium-term (a few weeks); | AR5: Compressed air-based technologies;Pumped hydro storage; | AS5: No | AU5: Capacity factor (max or nominal);Charge capacity (MW) (if it can be different from discharge capacity); | AW5: Capital cost;Variable O&M cost; | AX5: No (PCS and reservoir are treated with one cost value) | AY5: Power capacity-related (e.g., capacity firming); | AZ5: At the generation side (central power plants); | BA5: Energy-related services are modeled collectively.; | BB5: Back-up capacity (once or a few times a year);Capacity firming of non-VRE (e.g., day/night smoothing of nuclear power); | BC5: Not relevant; | BD5: Curtailment reduction; | BF5: Cost competetiveness (incl. capital cost, O&M cost, levelized cost, etc.) compared to other alternatives;Rapid cost learning, i.e., the decline of storage cost in future;The increasing share of VRE in the system (e.g., as % of annual load or generation); | BH5: Storage capacity/activity is dependent to that of VRE (i.e., no VRE --> no storage).;Storage capacity/activity is capped to a certain share of another process, such as generation, flexibility, T&D, load, etc. (e.g., max 40% of load can be met by storage discharge); | BI5: No, the contribution of storage is only allowed to certain services (e.g., either to energy- or capacity-related services). | BJ5: Storage contributes to the system-level benefits. | BL5: No, storage parameters were kept consistently across scenarios. | BM5: for now we didnt change storage parameters. | BN5: Capacity of storage (GWh);Lifetime of storage technologies (year);Power capacity of electricity storage (GW);
A6: 8 | B6: 45562.449 | C6: 45562.487 | D6: anonymous | G6: Amir Fattahi | H6: amir.fattahi@tno.nl | I6: TNO | J6: WP1 (Task 1.3); | K6: TIAM-ECN | L6: Integrated assessment model | M6: Investment and capacity exapnsion planning | N6: Global | O6: EU divided in 2-3 subregions | P6: Coarse copperplate (multiple countries in one modeling node) | Q6: cross-border lines are modelled between two subregions of EU (EastEU and WestEU) through an aggregated proxy. | R6: Perfect foresight | S6: 2- to 5-yearly;10-yearly and/or longer; | T6: ~2100 (full century) | U6: Seasonal (2-4 time slices per model period) | W6: No | X6: Not relevant (e.g., no temporal representation) | Y6: Only for solar and wind generation, we represent short-term events implicitly as an additional flexibility requirement costs. | Z6: Bidirectional soft-linking to a detailed operational and dispatch model;Using data from various empirical or model-based studies;We are doing a bidirectional soft-linking with a detailed power system model in WP3.2. It is a work in progress.. ; | AA6: Short- and long-term decisions are co-optimized in an integrated way. | AB6: No | AC6: None of the above or not relevant; | AD6: Scale-free technology types (e.g., different gas power plant types aggregated separately) | AE6: Buildings;Fossil fuel supply ;Heat supply (including district heating/cooling);Industry sector;Renewable-based fuels and derivatives (e.g., green hydrogen);Power (supply) sector;Transport sector; | AF6: Demand is modeled endogenously | AH6: Concentrated solar power (CSP) (w/o storage);Onshore wind;Offshore wind;Run-of-the-river hydropower (w/o storage);Solar photovoltaic (PV) (general); | AI6: Direct costs (capital, O&M, etc.);Indirect costs (integration costs);Technical characteristics (efficiency, capacity factor, etc.) ;Resource potential;Weather dependency (varying output in different time scales within a year); | AJ6: Additional O&M cost of non-VRE; | AL6: Yes (no need for generation from non-VRE or discharge from storage) | AM6: Integration cost (economic/implicit);Resource potential;Temporal or spatial mismatch between VRE and load; | AO6: Curtailment of VRE;Flexible electricity generation from thermal power (e.g., biomass, coal, gas) with or w/o CCS;Flexible electricity generation from nuclear power;Power to hydrogen (electrolyzers);Power to heat (w/ or w/o storage);Power to synfuels (other than hydrogen);Electricity export/import (grid connection); | AP6: No | AQ6: Storage duration does not play a role (e.g., storage is modeled generically); | AR6: No storage is modelled in TIAM-ECN. I have to give an answer to Q35 to continue the survey. ; | AS6: No | AU6: No storage is modelled in TIAM-ECN; | AV6: No storage is modelled in TIAM-ECN. | AW6: No storage is modelled in TIAM-ECN; | AX6: Cost of storage is not relevant or represented | AY6: Ancillary services (e.g., frequency regulation); | AZ6: Not relevant; | BA6: No storage is modelled in TIAM-ECN. Please ignore Q42 answer. I had to tick a box to continue the survey. ; | BB6: No storage is modelled in TIAM-ECN; | BC6: Not relevant; | BD6: No storage is modelled in TIAM-ECN; | BF6: Not relevant; | BH6: Not relevant; | BI6: Not relevant | BJ6: Not relevant | BL6: No, storage parameters were kept consistently across scenarios. | BM6: No storage is modelled in TIAM-ECN. | BN6: Power capacity of hydrogen electrolyzer (GW);Net electricity trade (import/export) (EJ/yr);
A7: 10 | B7: 45565.722 | C7: 45565.883 | D7: anonymous | G7: Robert Pietzcker | H7: pietzcker@pik-potsdam.de | I7: Potsdam Institute for Climate Impact Research | J7: WP1 (Task 1.3); | K7: REMIND | L7: Integrated assessment model | M7: Hybrid: coupling an investment and capacity expansion energy system with a Ramsey growth model | N7: Global | O7: Multiple-country (~1-4 EU countries in each model region) | P7: Coarse copperplate (multiple countries in one modeling node) | Q7: not explicitly modeled, but generalized transmission expansion and pooling effects across EU regions are included | R7: Perfect foresight | S7: 2- to 5-yearly; | T7: ~2100 (full century) | U7: Not explicitly, but the effects on VRE integration/storage/transmission build-out are represented in an aggregate way | V7: Not explicitly, but the effects on VRE integration/storage/transmission build-out are represented in an aggregate way, parameterized to reflect results from more detailed (hourly) models | W7: Other | X7: Not relevant (e.g., no temporal representation) | Y7: Short-term events are represented implicitly, e.g., as a cost or other proxy. | Z7: Using data from various empirical or model-based studies; | AA7: Short-term decisions are represented using proxies and/or in a stylized format as part of long-term decisionmaking | AB7: No | AC7: None of the above or not relevant; | AD7: Scale-free technology types (e.g., different gas power plant types aggregated separately) | AE7: Buildings;Fossil fuel supply ;Heat supply (including district heating/cooling);Industry sector;Renewable-based fuels and derivatives (e.g., green hydrogen);Power (supply) sector;Transport sector; | AF7: Demand is modeled endogenously | AH7: Concentrated solar power (CSP) (w/o storage);Onshore wind;Offshore wind;Run-of-the-river hydropower (w/o storage);Solar photovoltaic (PV) (general); | AI7: Resource potential;Indirect costs (integration costs);Direct costs (capital, O&M, etc.);Curtailment;Technical characteristics (efficiency, capacity factor, etc.) ; | AJ7: Curtailment cost (i.e., cost of handling excess electricity or negative prices);Grid expansion or fortification needs;Storage requirements for energy time-shifting; | AL7: Yes (but partly has to be with stored or firmed VRE) | AM7: Integration cost (economic/implicit);Minimum share of non-VRE technologies (e.g., stabilizing share, firm capacity, etc.);Integration requirements (technical/explicit, e.g., grid expansion and/or storage scale-up);Resource potential; | AN7: on question 31: what is "firmed VRE"? in our model, there has to be some storage discharge and there has to be some electricity generation from either gas peaking plants or hydrogen peaking plants - in ambitious mitigation scenarios, the model then only uses hydrogen peaking plants from electrolysis-hydrogen. is this "stored electricity", or is it "a level on non-VRE-generation"? | AO7: not explicitly modeled, but many of these options are contained in the models that were used to parameterize the integration constraints/storage/grid/curtailment; | AP7: Yes | AQ7: Storage duration does not play a role (e.g., storage is modeled generically); | AR7: Secondary electorchemical batteries (e.g., Li-ion, etc.);electrolyzers + h2 turbines; | AS7: No | AU7: Duration of discharge or energy-to-power ratio (h);Round-trip efficiency;Storage reservoir size (MWh);Discharge capacity (MW) (if it can be different from charge capacity); | AW7: Capital cost;Fixed O&M cost; | AX7: No (PCS and reservoir are treated with one cost value) | AY7: Renewable energy integration (e.g., curtailment reduction); | AZ7: Storage is represented generically (no location specific); | BA7: see below - not explicitly modeled; | BB7: see below - not explicitly modeled; | BC7: Not relevant; | BD7: VRE-related services of storage are modeled in an aggregated way (i.e., no individual representation of services).; | BE7: Storage deployment is modeled as a requirement from VRE deployment, with the specific storage requirements per kWh of VRE electricity increasing linearly with the share of VRE. (so in total, storage requirements increase roughly with the square of VRE share) | BF7: The increasing share of VRE in the system (e.g., as % of annual load or generation); | BH7: Storage capacity/activity is dependent to that of VRE (i.e., no VRE --> no storage).;Storage is constrained by build-up, technological learning, and/or market-penetration growth rates (i.e., dynamic constraints dependent on storage deployment).; | BI7: as said above, storage is directly hard-linked to VRE deployment | BJ7: Not relevant | BL7: Yes | BM7: yes, we decrease the storage capacity requirements at a given VRE share, as we assume more demand side management, better use of vehicle-to-grid, better pooling etc. | BN7: Capacity of storage (GWh);Capital cost of storage technologies (EUR/GW or EUR/GWh);Duration of charge/discharge (h);Power capacity of electricity storage (GW);Power capacity of hydrogen electrolyzer (GW);
A8: 11 | B8: 45570.865 | C8: 45570.881 | D8: anonymous | G8: Behnam Zakeri | H8: zakeri@iiasa.ac.at | I8: IIASA | J8: WP1 (Task 1.3);WP5; | K8: MESSAGEix-GLOBIOM | L8: Integrated assessment model | M8: Investment and capacity exapnsion planning | N8: Global | O8: EU divided in 2-3 subregions | P8: Coarse copperplate (multiple countries in one modeling node) | Q8: Using proxies or stylized methods | R8: Perfect foresight | S8: 2- to 5-yearly;10-yearly and/or longer; | T8: ~2100 (full century) | U8: Yearly (No sub-annual time slices) | Y8: Short-term events are represented implicitly, e.g., as a cost or other proxy. | Z8: Using data from various empirical or model-based studies;Using data from a detailed operational and dispatch model (unidirectional soft-linking); | AA8: Short-term decisions are represented using proxies and/or in a stylized format as part of long-term decisionmaking | AB8: Applying peak load factors to cover grid contingencies and uncertainties in load | AC8: None of the above or not relevant; | AD8: Scale-free technology types (e.g., different gas power plant types aggregated separately) | AE8: Buildings;Fossil fuel supply ;Heat supply (including district heating/cooling);Industry sector;Renewable-based fuels and derivatives (e.g., green hydrogen);Power (supply) sector;Transport sector; | AF8: Elastic demand (responsive to supply cost) | AH8: Concentrated solar power (CSP) (w/o storage);Onshore wind;Offshore wind;Run-of-the-river hydropower (w/o storage);Solar photovoltaic (PV) (general); | AI8: Capacity value (contribution to power adequacy);Curtailment;Direct costs (capital, O&M, etc.);Indirect costs (integration costs);Resource potential;Technical characteristics (efficiency, capacity factor, etc.) ; | AJ8: Additional ancillary/balancing services costs (economic);Curtailment cost (i.e., cost of handling excess electricity or negative prices);Grid management/contingency costs;Grid expansion or fortification needs;Reduced capacity factor of non-VRE;Short-term flexibility requirements; | AL8: Yes (but partly has to be with stored or firmed VRE) | AM8: Minimum share of non-VRE technologies (e.g., stabilizing share, firm capacity, etc.);Integration cost (economic/implicit);Integration requirements (technical/explicit, e.g., grid expansion and/or storage scale-up);Resource potential; | AO8: Curtailment of VRE;Demand response in transport (e.g., smart charging of EVs);Electricity storage;Electricity export/import (grid connection);Flexible electricity generation from thermal power (e.g., biomass, coal, gas) with or w/o CCS;Flexible electricity generation from hydropower;Power to hydrogen (electrolyzers); | AP8: Yes | AQ8: Short-term (hours to a few days);Long-term (months to seasons); | AR8: Storage is represented as a generic or homogenous asset w/o specific technology types.; | AS8: No | AU8: Capacity factor (max or nominal);Lifetime (in years);Power capacity (MW) (used for both charge and discharge);Round-trip efficiency; | AW8: Capital cost;Variable O&M cost;Fixed O&M cost;Replacement or major retrofit cost; | AX8: No (PCS and reservoir are treated with one cost value) | AY8: Energy-related (e.g., peak shaving);Power capacity-related (e.g., capacity firming);T&D grid (e.g., investment deferral);Renewable energy integration (e.g., curtailment reduction);Ancillary services (e.g., frequency regulation); | AZ8: At the generation side (central power plants);At the generation side (utility VRE);Power transmission level; | BA8: Energy-related services are modeled collectively.; | BB8: Capacity-related services are modeled collectively.; | BC8: Grid services are modeled collectively.; | BD8: Curtailment reduction;Integration cost reduction;Short-term flexibility/balancing (operative reserve);Capacity firming (increasing capacity value of VRE); | BF8: Cost competetiveness (incl. capital cost, O&M cost, levelized cost, etc.) compared to other alternatives;Rapid cost learning, i.e., the decline of storage cost in future;The increasing share of VRE in the system (e.g., as % of annual load or generation);The value of capacity services of storage;Barriers in the deployment of competing technologies (e.g., demand response, grid expansion, etc.);Considering the duration of storage services (short vs. long duration); | BH8: Storage can be deployed in competition with other alternatives, without any specific limit.;Storage is constrained by build-up, technological learning, and/or market-penetration growth rates (i.e., dynamic constraints dependent on storage deployment).; | BI8: Yes, storage can provide multiple services without any limits. | BJ8: Storage contributes to the system-level benefits. | BL8: No, storage parameters were kept consistently across scenarios. | BM8: N/A | BN8: Capacity of storage (GWh);Capital cost of storage technologies (EUR/GW or EUR/GWh);Efficiency of storage technologies (as % or lost energy (EJ/yr));Lifetime of storage technologies (year);Net electricity trade (import/export) (EJ/yr);Power capacity of electricity storage (GW);Power capacity of hydrogen electrolyzer (GW);
A9: 13 | B9: 45999.111 | C9: 45999.36 | D9: anonymous | G9: Shotaro Mori | H9: mori.shotaro.2n@kyoto-u.ac.jp | I9: Kyoto University | J9: Not participated in ECEMF; | K9: AIM | L9: Integrated assessement model soft-linked with energy system model | M9: Macro-economic modeling & Investment and capacity expansion planning | N9: Global | O9: EU divided in 2-3 subregions | P9: Coarse copperplate (multiple countries in one modeling node) | Q9: Not modeled | R9: Recursive dynamic (feedback loop) | S9: Yearly; | T9: ~2100 (full century) | U9: Representative time slices (sampled or clustered) | V9: In our model, intra-annual time is represented using representative time slices. The year is approximated by twelve representative days, one for each month, and each representative day is modeled with twenty-four hourly slices, so the time-slice length is one hour. In addition, the model includes four extra representative days, one in each quarter, selected to reflect conditions when VRE output is at its lowest based on historical weather data from 2006 to 2015. | W9: No | X9: No, the concurrency is not preserved (e.g., due to sampling) | Y9: Short-term events are not represented or relevant. | AD9: Scale-free technology types (e.g., different gas power plant types aggregated separately) | AE9: Buildings;Fossil fuel supply ;Heat supply (including district heating/cooling);Industry sector;Renewable-based fuels and derivatives (e.g., green hydrogen);Power (supply) sector;Transport sector; | AF9: Demand is modeled endogenously | AH9: Solar photovoltaic (PV) (rooftop);Solar photovoltaic (PV) (utility);Offshore wind;Onshore wind;Concentrated solar power (CSP) (w/o storage); | AI9: Capacity value (contribution to power adequacy);Curtailment;Resource potential;Technical characteristics (efficiency, capacity factor, etc.) ;Weather dependency (varying output in different time scales within a year);Direct costs (capital, O&M, etc.); | AJ9: Short-term flexibility requirements;Storage requirements for energy time-shifting; | AK9: The power sector uses a dispatch module with a 1 hour temporal resolution for representative days. The operating conditions of the power generator are determined under a cost-minimizing framework subject to satisfying the power supply–demand balance. Therefore, the capacity factor of flexible generators, storage requirements and other flexibility requirements (e.g., demand response) are determined endogenously in this model. | AL9: Yes (no need for generation from non-VRE or discharge from storage) | AM9: Integration requirements (technical/explicit, e.g., grid expansion and/or storage scale-up);Resource potential;Temporal or spatial mismatch between VRE and load; | AO9: Curtailment of VRE;Demand response in buildings;Demand response in transport (e.g., smart charging of EVs);Electricity storage;Flexible electricity generation from thermal power (e.g., biomass, coal, gas) with or w/o CCS;Power to hydrogen (electrolyzers);Power to synfuels (other than hydrogen); | AP9: Yes | AQ9: Long-term (months to seasons);Short-term (hours to a few days); | AR9: Pumped hydro storage;Secondary electorchemical batteries (e.g., Li-ion, etc.);Compressed air-based technologies; | AS9: No | AU9: Power capacity (MW) (used for both charge and discharge);Duration of discharge or energy-to-power ratio (h);Round-trip efficiency;Storage reservoir size (MWh);Lifetime (in years); | AW9: Capital cost;Fixed O&M cost; | AX9: No (PCS and reservoir are treated with one cost value) | AY9: Energy-related (e.g., peak shaving);Power capacity-related (e.g., capacity firming);Renewable energy integration (e.g., curtailment reduction); | AZ9: Storage is represented generically (no location specific); | BA9: Energy time shifting (arbitrage);Peak shaving (e.g., daily, seasonal);Energy-related services are modeled collectively.; | BB9: Back-up capacity (once or a few times a year);Capacity firming of non-VRE (e.g., day/night smoothing of nuclear power);Capacity-related services are modeled collectively.; | BC9: Investment in storage has no impact on T&D.; | BD9: VRE-related services of storage are modeled in an aggregated way (i.e., no individual representation of services).;Curtailment reduction;Energy time-shifting;Short-term flexibility/balancing (operative reserve);Capacity firming (increasing capacity value of VRE); | BE9: Potentially, energy storage in our model could provide the services ticked in Q.44, Q.45, and Q.47, however, these are not modeled as explicit, disaggregated services. Rather, in our model, energy storage is represented only as a device that can charge and discharge energy within the optimization of power system operation, and it is only ex post that storage is interpreted as having provided such services. | BF9: Cost competetiveness (incl. capital cost, O&M cost, levelized cost, etc.) compared to other alternatives;Considering the duration of storage services (short vs. long duration);Rapid cost learning, i.e., the decline of storage cost in future;The increasing share of VRE in the system (e.g., as % of annual load or generation);The value of capacity services of storage;Barriers in the deployment of competing technologies (e.g., demand response, grid expansion, etc.);Increased volatility in the pattern of electric load within a year;Increased variability in the pattern of VRE within a year; | BH9: (Some or all) storage technologies are constrained by available sites, resource potential, material availability, etc. (i.e., static constraints not necessarily dependent on storage deployment); | BI9: Yes, storage can provide multiple services without any limits. | BJ9: Storage contributes to the system-level benefits. | BL9: No, storage parameters were kept consistently across scenarios. | BM9: In our model, the techno-economic parameters of storage technologies are basically kept identical across scenarios. | BN9: Not participated in ECEMF;
A10: 14 | B10: 46013.77 | C10: 46013.842 | D10: anonymous | G10: Matthew Binsted | H10: matthew.binsted@pnnl.gov | I10: Pacific Northwest National Laboratory | J10: unsure (not involved in ECEMF); | K10: Global Change Analysis Model (GCAM) | L10: Integrated assessment model | M10: Market simulation | N10: Global | O10: EU divided in 2-3 subregions | P10: Coarse copperplate (multiple countries in one modeling node) | Q10: Not modeled | R10: Recursive dynamic (feedback loop) | S10: 2- to 5-yearly; | T10: ~2100 (full century) | U10: Yearly (No sub-annual time slices) | Y10: Short-term events are not represented or relevant. | AD10: Scale-free technology types (e.g., different gas power plant types aggregated separately) | AE10: Buildings;Fossil fuel supply ;Heat supply (including district heating/cooling);Industry sector;Renewable-based fuels and derivatives (e.g., green hydrogen);Power (supply) sector;Transport sector; | AF10: Demand is modeled endogenously | AH10: Concentrated solar power (CSP) (w/o storage);Onshore wind;Offshore wind;Solar photovoltaic (PV) (rooftop);Solar photovoltaic (PV) (utility); | AI10: Direct costs (capital, O&M, etc.);Indirect costs (integration costs);Resource potential;Technical characteristics (efficiency, capacity factor, etc.) ; | AJ10: GCAM v7.3+ represents diminishing VRE value with increasing VRE generation share - reflective of a variety of system costs needed to support VRE integration (VRE curtailment, additional firm capacity, transmission expansion, ancillary/balancing services costs, etc.). This value reduction is represented as a single integration cost added to other technology costs (capital, O&M, grid connection, etc.).;Additional ancillary/balancing services costs (economic);Curtailment cost (i.e., cost of handling excess electricity or negative prices);Grid expansion or fortification needs;Grid management/contingency costs; | AL10: Yes (but partly has to be with stored or firmed VRE) | AM10: Integration cost (economic/implicit);Resource potential; | AN10: GCAM v7.3+ represents diminishing VRE value with increasing VRE generation share - reflective of a variety of system costs needed to support VRE integration (VRE curtailment, additional firm capacity, transmission expansion, ancillary/balancing services costs, etc.). This value reduction is represented as a single integration cost added to other technology costs (capital, O&M, grid connection, etc.). This approach is documented at https://jgcri.github.io/gcam-doc/cmp/394-Intermittent_electricity_integration.pdf and is based on technology market share : value factor relationships from Mowers et al., 2023 (Mowers, M., Mignone, B.K. and Steinberg, D.C., 2023. Quantifying value and representing competitiveness of electricity system technologies in economic models. Applied Energy, 329, p.120132. https://doi.org/10.1016/j.apenergy.2022.120132.). | AO10: GCAM represents annual electricity generation by technology and does not explicitly balance electric loads subannually.; | AP10: Yes | AQ10: Short-term (hours to a few days);Storage duration does not play a role (e.g., storage is modeled generically); | AR10: Secondary electorchemical batteries (e.g., Li-ion, etc.);Storage is represented as a generic or homogenous asset w/o specific technology types.;In GCAM, storage is represented generically but parameterized based on a short-duration Li-ion battery system for PV and onshore wind and molten salt thermal storage for CSP.; | AS10: No | AU10: Lifetime (in years);Replacement (partial or full);Round-trip efficiency; | AW10: Capital cost;Variable O&M cost;Fixed O&M cost;Replacement or major retrofit cost; | AX10: No (PCS and reservoir are treated with one cost value) | AY10: Renewable energy integration (e.g., curtailment reduction); | AZ10: At the generation side (utility VRE); | BA10: Energy-related services are not relevant/modeled.; | BB10: Capacity-related services are modeled collectively.; | BC10: Not relevant; | BD10: Curtailment reduction;Integration cost reduction;VRE-related services of storage are modeled in an aggregated way (i.e., no individual representation of services).; | BE10: For variable renewable energy technologies (e.g., PV, CSP, onshore wind), GCAM represents two technology options: (1) VRE without dedicated storage which is subject to integration costs (reduced value factor with increasing market share) or (2) VRE with dedicated storage (short-duration Li-ion battery for PV and onshore wind; molten salt thermal storage for CSP) which entail additional capital and O&M costs and round trip energy losses but do not face any integration costs. | BF10: Cost competetiveness (incl. capital cost, O&M cost, levelized cost, etc.) compared to other alternatives;The increasing share of VRE in the system (e.g., as % of annual load or generation); | BH10: Storage capacity/activity is dependent to that of VRE (i.e., no VRE --> no storage).; | BI10: Not relevant | BJ10: Depending on the location of storage, it can be owned by the grid, energy utilites, or end user, and would benefit the respective owner. | BL10: Yes | BM10: I am not personally involved in ECEMF and am not aware of GCAM involvement. I answered Yes to question 49 since N/A was not an option. GCAM does include central, high, and low cost storage assumptions that can be used in different scenarios. | BN10: Not participated in ECEMF;

Sheet summary
A1: Metadata | B1: VRE | C1: Storage | D1: The name of the modeling tool for which you fill out the survey: | E1: AIM | F1: GCAM | G1: IMAGE | H1: MESSAGEix-GLOBIOM | I1: PROMETHEUS | J1: REMIND | K1: TIAM-ECN | L1: WITCH
D2: What is the main category of the model? | E2: Integrated assessement model soft-linked with energy system model | F2: Integrated assessment model | G2: Integrated assessment model | H2: Integrated assessment model | I2: Integrated assessment model | J2: Integrated assessment model | K2: Integrated assessment model | L2: Integrated assessment model
A3: 1 | D3: What option describes your modeling approach best? | E3: Macro-economic modeling & Investment and capacity expansion planning | F3: Market simulation | G3: Investment and capacity exapnsion planning | H3: Investment and capacity exapnsion planning | I3: Market simulation | J3: Hybrid: coupling an investment and capacity expansion energy system with a Ramsey growth model | K3: Investment and capacity exapnsion planning | L3: Macro-economic modeling
D4: What geographical scope presents your model best? | E4: Global | F4: Global | G4: Global | H4: Global | I4: Global | J4: Global | K4: Global | L4: Global
A5: 1 | D5: What is the spatial resolution of your model concerning the EU region? | E5: EU divided in 2-3 subregions | F5: EU divided in 2-3 subregions | G5: EU divided in 2-3 subregions | H5: EU divided in 2-3 subregions | I5: EU divided in 2-3 subregions | J5: Multiple-country (~1-4 EU countries in each model region) | K5: EU divided in 2-3 subregions | L5: EU- or European level (one model region)
A6: 1 | D6: What level(s) of the electricity network is represented in your model? | E6: Coarse copperplate (multiple countries in one modeling node) | F6: Coarse copperplate (multiple countries in one modeling node) | G6: Coarse copperplate (multiple countries in one modeling node) | H6: Coarse copperplate (multiple countries in one modeling node) | I6: Coarse copperplate (multiple countries in one modeling node) | J6: Coarse copperplate (multiple countries in one modeling node) | K6: Coarse copperplate (multiple countries in one modeling node) | L6: Coarse copperplate (multiple countries in one modeling node)
A7: 1 | D7: How are cross-border transmission lines between EU countries represented in your model? | E7: Not modeled | F7: Not modeled | G7: Using proxies or stylized methods | H7: Using proxies or stylized methods | I7: Not modeled | J7: not explicitly modeled, but generalized transmission expansion and pooling effects across EU regions are included | K7: cross-border lines are modelled between two subregions of EU (EastEU and WestEU) through an aggregated proxy. | L7: Not modeled
A8: 1 | D8: How the planning foresight is treated in your model: | E8: Recursive dynamic (feedback loop) | F8: Recursive dynamic (feedback loop) | G8: Recursive dynamic (feedback loop) | H8: Perfect foresight | I8: Myopic foresight (short sighted) | J8: Perfect foresight | K8: Perfect foresight | L8: Perfect foresight
D9: What time intervals are considered in the model horizon? (Please tick all that apply) | E9: Yearly; | F9: 2- to 5-yearly; | G9: Yearly; | H9: 2- to 5-yearly;10-yearly and/or longer; | I9: Yearly; | J9: 2- to 5-yearly; | K9: 2- to 5-yearly;10-yearly and/or longer; | L9: 2- to 5-yearly;
D10: What planning/modeling horizon is used in your analysis? | E10: ~2100 (full century) | F10: ~2100 (full century) | G10: ~2100 (full century) | H10: ~2100 (full century) | I10: ~2050 (mid century) | J10: ~2100 (full century) | K10: ~2100 (full century) | L10: ~2100 (full century)
A11: 1 | D11: How is the sub-annual temporal resolution represented in your model? | E11: Representative time slices (sampled or clustered) | F11: Yearly (No sub-annual time slices) | G11: Multi-hourly | H11: Yearly (No sub-annual time slices) | I11: Yearly (No sub-annual time slices) | J11: Not explicitly, but the effects on VRE integration/storage/transmission build-out are represented in an aggregate way | K11: Seasonal (2-4 time slices per model period) | L11: Yearly (No sub-annual time slices)
D12: If you answered "Representative time slices" or "Other", please explain. For example, the method of sampling/clustering and/or the length of time slices. | E12: In our model, intra-annual time is represented using representative time slices. The year is approximated by twelve representative days, one for each month, and each representative day is modeled with twenty-four hourly slices, so the time-slice length is one hour. In addition, the model includes four extra representative days, one in each quarter, selected to reflect conditions when VRE output is at its lowest based on historical weather data from 2006 to 2015. | J12: Not explicitly, but the effects on VRE integration/storage/transmission build-out are represented in an aggregate way, parameterized to reflect results from more detailed (hourly) models
A13: 1 | D13: Is the chronology of (sub-annual) time slices preserved in your modeling work? | E13: No | G13: No | J13: Other | K13: No
A14: 1 | D14: Is the joint variability of supply and demand resources in each sub-annual time slice captured in your model? This means, e.g., the timeseries of wind, solar PV, and demand are all concurrent with... | E14: No, the concurrency is not preserved (e.g., due to sampling) | G14: Yes, although the demand pattern is historic and not based on endogenous demand sector developments | J14: Not relevant (e.g., no temporal representation) | K14: Not relevant (e.g., no temporal representation)
A15: 1 | D15: How are short-term operational events represented in your model? Short-term decisions are in the scale of hours to a few days including generator scheduling, ramping rates, flexibility requirement... | E15: Short-term events are not represented or relevant. | F15: Short-term events are not represented or relevant. | G15: A few extreme short-term events are represented explicitly (e.g., seasonal peak load and zero supply from renewables). | H15: Short-term events are represented implicitly, e.g., as a cost or other proxy. | I15: Short-term events are represented implicitly, e.g., as a cost or other proxy. | J15: Short-term events are represented implicitly, e.g., as a cost or other proxy. | K15: Only for solar and wind generation, we represent short-term events implicitly as an additional flexibility requirement costs. | L15: Short-term events are represented implicitly, e.g., as a cost or other proxy.
A16: 1 | D16: If short-term decisions are not represented explicitly in your model, how is the relevant parametrization done? Check all relevant answers. | G16: Using data from various empirical or model-based studies;We use the RLDC dataset developed by PIK during the ADVANCE project (Ueckerdt et al., 2016); | H16: Using data from various empirical or model-based studies;Using data from a detailed operational and dispatch model (unidirectional soft-linking); | I16: Using data from various empirical or model-based studies; | J16: Using data from various empirical or model-based studies; | K16: Bidirectional soft-linking to a detailed operational and dispatch model;Using data from various empirical or model-based studies;We are doing a bidirectional soft-linking with a detailed power system model in WP3.2. It is a work in progress.. ; | L16: Using data from various empirical or model-based studies;
A17: 1 | D17: How are short-term decisions linked to long-term infrastructure planning and investment decisions in your model? Long-term decisions refer to multi-decadal decisions such as investment in power pl... | G17: Short-term decisions are represented using proxies and/or in a stylized format as part of long-term decisionmaking | H17: Short-term decisions are represented using proxies and/or in a stylized format as part of long-term decisionmaking | I17: Short-term decisions are represented using proxies and/or in a stylized format as part of long-term decisionmaking | J17: Short-term decisions are represented using proxies and/or in a stylized format as part of long-term decisionmaking | K17: Short- and long-term decisions are co-optimized in an integrated way. | L17: Short-term decisions are not relevant to the modeling scope.
A18: 1 | D18: Is the weather uncertainty in multiple years included in your model parameters? | G18: Data of one representative year based on irradiation and wind speed data for 1984–2005 | H18: Applying peak load factors to cover grid contingencies and uncertainties in load | I18: Yes, using varying input data (or sensitivity analysis) | J18: No | K18: No | L18: No
D19: What future uncertainties are considered when representing sub-annual temporal variability in your model parameters? Here, we refer to those events not driven by socioeconomic developments or cost... | G19: None of the above or not relevant; | H19: None of the above or not relevant; | I19: Climate impact on the supply side;Climate impact on the demand side; | J19: None of the above or not relevant; | K19: None of the above or not relevant; | L19: Climate impact on the supply side;Climate impact on the demand side;
D20: What is the level of granularity in representing technologies in your model? | E20: Scale-free technology types (e.g., different gas power plant types aggregated separately) | F20: Scale-free technology types (e.g., different gas power plant types aggregated separately) | G20: Scale-free technology types (e.g., different gas power plant types aggregated separately) | H20: Scale-free technology types (e.g., different gas power plant types aggregated separately) | I20: Technologies by input fuel type (e.g., all gas power plant types aggregated together) | J20: Scale-free technology types (e.g., different gas power plant types aggregated separately) | K20: Scale-free technology types (e.g., different gas power plant types aggregated separately) | L20: Technologies by input fuel type (e.g., all gas power plant types aggregated together)
D21: Which of the following demand and supply-side sectors are included in your model? Please choose all that apply. | E21: Buildings;Fossil fuel supply ;Heat supply (including district heating/cooling);Industry sector;Renewable-based fuels and derivatives (e.g., green hydrogen);Power (supply) sector;Transport sector; | F21: Buildings;Fossil fuel supply ;Heat supply (including district heating/cooling);Industry sector;Renewable-based fuels and derivatives (e.g., green hydrogen);Power (supply) sector;Transport sector; | G21: Buildings;Fossil fuel supply ;Heat supply (including district heating/cooling);Industry sector;Renewable-based fuels and derivatives (e.g., green hydrogen);Power (supply) sector;Transport sector; | H21: Buildings;Fossil fuel supply ;Heat supply (including district heating/cooling);Industry sector;Renewable-based fuels and derivatives (e.g., green hydrogen);Power (supply) sector;Transport sector; | I21: Buildings;Fossil fuel supply ;Industry sector;Renewable-based fuels and derivatives (e.g., green hydrogen);Power (supply) sector;Transport sector; | J21: Buildings;Fossil fuel supply ;Heat supply (including district heating/cooling);Industry sector;Renewable-based fuels and derivatives (e.g., green hydrogen);Power (supply) sector;Transport sector; | K21: Buildings;Fossil fuel supply ;Heat supply (including district heating/cooling);Industry sector;Renewable-based fuels and derivatives (e.g., green hydrogen);Power (supply) sector;Transport sector; | L21: Buildings;Power (supply) sector;Transport sector;
A22: 1 | D22: How electricity demand is represented in your model? | E22: Demand is modeled endogenously | F22: Demand is modeled endogenously | G22: Depends on the sector. Some are modelled in much detail (transport, industry), while other are more aggregated | H22: Elastic demand (responsive to supply cost) | I22: Demand is modeled endogenously | J22: Demand is modeled endogenously | K22: Demand is modeled endogenously | L22: Static demand (no response to supply cost)
D23: If your answer was "Other", please explain: | G23: Depends on the sector. Some are modelled in much detail (transport, industry), while other are more aggregated
B24: 1 | D24: Which VRE sources are represented in your model? Please choose all that apply. | E24: Solar photovoltaic (PV) (rooftop);Solar photovoltaic (PV) (utility);Offshore wind;Onshore wind;Concentrated solar power (CSP) (w/o storage); | F24: Concentrated solar power (CSP) (w/o storage);Onshore wind;Offshore wind;Solar photovoltaic (PV) (rooftop);Solar photovoltaic (PV) (utility); | G24: Concentrated solar power (CSP) (w/o storage);Onshore wind;Offshore wind;Run-of-the-river hydropower (w/o storage);Solar photovoltaic (PV) (general);Solar photovoltaic (PV) (rooftop);Solar photovoltaic (PV) (utility);Tidal or marine energy; | H24: Concentrated solar power (CSP) (w/o storage);Onshore wind;Offshore wind;Run-of-the-river hydropower (w/o storage);Solar photovoltaic (PV) (general); | I24: Concentrated solar power (CSP) (w/o storage);Onshore wind;Offshore wind;Solar photovoltaic (PV) (general); | J24: Concentrated solar power (CSP) (w/o storage);Onshore wind;Offshore wind;Run-of-the-river hydropower (w/o storage);Solar photovoltaic (PV) (general); | K24: Concentrated solar power (CSP) (w/o storage);Onshore wind;Offshore wind;Run-of-the-river hydropower (w/o storage);Solar photovoltaic (PV) (general); | L24: Concentrated solar power (CSP) (w/o storage);Onshore wind;Offshore wind;Solar photovoltaic (PV) (general);
B25: 1 | D25: What aspect(s) of VRE is represented in the model? Please choose all that apply. | E25: Capacity value (contribution to power adequacy);Curtailment;Resource potential;Technical characteristics (efficiency, capacity factor, etc.) ;Weather dependency (varying output in different time scales within a year);Direct costs (capital, O&M, etc.); | F25: Direct costs (capital, O&M, etc.);Indirect costs (integration costs);Resource potential;Technical characteristics (efficiency, capacity factor, etc.) ; | G25: Capacity value (contribution to power adequacy);Curtailment;Direct costs (capital, O&M, etc.);Indirect costs (integration costs);Resource potential;Technical characteristics (efficiency, capacity factor, etc.) ;Weather dependency (varying output in different time scales within a year); | H25: Capacity value (contribution to power adequacy);Curtailment;Direct costs (capital, O&M, etc.);Indirect costs (integration costs);Resource potential;Technical characteristics (efficiency, capacity factor, etc.) ; | I25: Direct costs (capital, O&M, etc.);Indirect costs (integration costs);Resource potential;Technical characteristics (efficiency, capacity factor, etc.) ;Weather dependency (varying output in different time scales within a year); | J25: Resource potential;Indirect costs (integration costs);Direct costs (capital, O&M, etc.);Curtailment;Technical characteristics (efficiency, capacity factor, etc.) ; | K25: Direct costs (capital, O&M, etc.);Indirect costs (integration costs);Technical characteristics (efficiency, capacity factor, etc.) ;Resource potential;Weather dependency (varying output in different time scales within a year); | L25: Capacity value (contribution to power adequacy);Curtailment;Direct costs (capital, O&M, etc.);Indirect costs (integration costs);Resource potential;
B26: 1 | D26: What VRE integration costs or requirements are modeled explicitly, i.e., depending on the capacity/generation of VRE? Please choose all that apply. | E26: Short-term flexibility requirements;Storage requirements for energy time-shifting; | F26: GCAM v7.3+ represents diminishing VRE value with increasing VRE generation share - reflective of a variety of system costs needed to support VRE integration (VRE curtailment, additional firm capacity, transmission expansion, ancillary/balancing services costs, etc.). This value reduction is represented as a single integration cost added to other technology costs (capital, O&M, grid connection, etc.).;Additional ancillary/balancing services costs (economic);Curtailment cost (i.e., cost of handling excess electricity or negative prices);Grid expansion or fortification needs;Grid management/contingency costs; | G26: Curtailment cost (i.e., cost of handling excess electricity or negative prices);Grid expansion or fortification needs;Reduced capacity factor of non-VRE;Storage requirements for energy time-shifting; | H26: Additional ancillary/balancing services costs (economic);Curtailment cost (i.e., cost of handling excess electricity or negative prices);Grid management/contingency costs;Grid expansion or fortification needs;Reduced capacity factor of non-VRE;Short-term flexibility requirements; | I26: Grid management/contingency costs;Additional ancillary/balancing services costs (economic);Reduced capacity factor of non-VRE; | J26: Curtailment cost (i.e., cost of handling excess electricity or negative prices);Grid expansion or fortification needs;Storage requirements for energy time-shifting; | K26: Additional O&M cost of non-VRE; | L26: Curtailment cost (i.e., cost of handling excess electricity or negative prices);Grid expansion or fortification needs;
D27: Please explain the representation of VRE integration in your model, if it cannot be described by the options above or in case of ticking "Other". | E27: The power sector uses a dispatch module with a 1 hour temporal resolution for representative days. The operating conditions of the power generator are determined under a cost-minimizing framework subject to satisfying the power supply–demand balance. Therefore, the capacity factor of flexible generators, storage requirements and other flexibility requirements (e.g., demand response) are determined endogenously in this model.
B28: 1 | D28: Can load be technically met only by VRE in a given (sub-annual) time slice in your model? | E28: Yes (no need for generation from non-VRE or discharge from storage) | F28: Yes (but partly has to be with stored or firmed VRE) | G28: Yes (no need for generation from non-VRE or discharge from storage) | H28: Yes (but partly has to be with stored or firmed VRE) | I28: Yes (but partly has to be with stored or firmed VRE) | J28: Yes (but partly has to be with stored or firmed VRE) | K28: Yes (no need for generation from non-VRE or discharge from storage) | L28: No (there must be a level of non-VRE generation)
B29: 1 | D29: What constraints limit the penetration of VRE in your model? Please choose all that apply. | E29: Integration requirements (technical/explicit, e.g., grid expansion and/or storage scale-up);Resource potential;Temporal or spatial mismatch between VRE and load; | F29: Integration cost (economic/implicit);Resource potential; | G29: Integration requirements (technical/explicit, e.g., grid expansion and/or storage scale-up);Resource potential;Integration cost (economic/implicit); | H29: Minimum share of non-VRE technologies (e.g., stabilizing share, firm capacity, etc.);Integration cost (economic/implicit);Integration requirements (technical/explicit, e.g., grid expansion and/or storage scale-up);Resource potential; | I29: Integration cost (economic/implicit);Resource potential;Maximum share of VRE (either from generation, load, input to T&D, etc.); | J29: Integration cost (economic/implicit);Minimum share of non-VRE technologies (e.g., stabilizing share, firm capacity, etc.);Integration requirements (technical/explicit, e.g., grid expansion and/or storage scale-up);Resource potential; | K29: Integration cost (economic/implicit);Resource potential;Temporal or spatial mismatch between VRE and load; | L29: Maximum share of VRE (either from generation, load, input to T&D, etc.);
D30: Please explain any additional points considering the constraints in your model that would limit the penetration of VRE, e.g., to meet 100% of the load. | F30: GCAM v7.3+ represents diminishing VRE value with increasing VRE generation share - reflective of a variety of system costs needed to support VRE integration (VRE curtailment, additional firm capacity, transmission expansion, ancillary/balancing services costs, etc.). This value reduction is represented as a single integration cost added to other technology costs (capital, O&M, grid connection, etc.). This approach is documented at https://jgcri.github.io/gcam-doc/cmp/394-Intermittent_electricity_integration.pdf and is based on technology market share : value factor relationships from Mowers et al., 2023 (Mowers, M., Mignone, B.K. and Steinberg, D.C., 2023. Quantifying value and representing competitiveness of electricity system technologies in economic models. Applied Energy, 329, p.120132. https://doi.org/10.1016/j.apenergy.2022.120132.). | G30: At some point, the load factor of any marginal solar/wind capacity gets quite small due to curtailments. Also, VRE can be backup for VRE. However, the firm capacity of marginal solar/wind capacity also gets quite low (increasing backup costs) | J30: on question 31: what is "firmed VRE"? in our model, there has to be some storage discharge and there has to be some electricity generation from either gas peaking plants or hydrogen peaking plants - in ambitious mitigation scenarios, the model then only uses hydrogen peaking plants from electrolysis-hydrogen. is this "stored electricity", or is it "a level on non-VRE-generation"?
B31: 1 | D31: How the mismatch between electricity from VRE and load can be balanced in your model? Please choose all that apply. | E31: Curtailment of VRE;Demand response in buildings;Demand response in transport (e.g., smart charging of EVs);Electricity storage;Flexible electricity generation from thermal power (e.g., biomass, coal, gas) with or w/o CCS;Power to hydrogen (electrolyzers);Power to synfuels (other than hydrogen); | F31: GCAM represents annual electricity generation by technology and does not explicitly balance electric loads subannually.; | G31: Curtailment of VRE;Electricity storage;Flexible electricity generation from thermal power (e.g., biomass, coal, gas) with or w/o CCS;Flexible electricity generation from hydropower;Flexible electricity generation from nuclear power;Power to hydrogen (electrolyzers); | H31: Curtailment of VRE;Demand response in transport (e.g., smart charging of EVs);Electricity storage;Electricity export/import (grid connection);Flexible electricity generation from thermal power (e.g., biomass, coal, gas) with or w/o CCS;Flexible electricity generation from hydropower;Power to hydrogen (electrolyzers); | I31: Electricity storage;Power to hydrogen (electrolyzers); | J31: not explicitly modeled, but many of these options are contained in the models that were used to parameterize the integration constraints/storage/grid/curtailment; | K31: Curtailment of VRE;Flexible electricity generation from thermal power (e.g., biomass, coal, gas) with or w/o CCS;Flexible electricity generation from nuclear power;Power to hydrogen (electrolyzers);Power to heat (w/ or w/o storage);Power to synfuels (other than hydrogen);Electricity export/import (grid connection); | L31: Curtailment of VRE;Electricity storage;
C32: 1 | D32: Have you explicitly modeled one or several electricity storage technologies in your model? | E32: Yes | F32: Yes | G32: No, storage is modeled as cost or other proxy | H32: Yes | I32: Yes | J32: Yes | K32: No | L32: No, storage is modeled as cost or other proxy
C33: 1 | D33: What forms of storage duration are considered in your model? The storage duration can be attributed to the choice of technology, e.g., batteries for the short and pumped hydro for the long term. P... | E33: Long-term (months to seasons);Short-term (hours to a few days); | F33: Short-term (hours to a few days);Storage duration does not play a role (e.g., storage is modeled generically); | G33: Short-term (hours to a few days);Medium-term (a few weeks);Long-term (months to seasons); | H33: Short-term (hours to a few days);Long-term (months to seasons); | I33: Short-term (hours to a few days);Long-term (months to seasons); | J33: Storage duration does not play a role (e.g., storage is modeled generically); | K33: Storage duration does not play a role (e.g., storage is modeled generically); | L33: Long-term (months to seasons);Medium-term (a few weeks);
C34: 1 | D34: What storage technology categories are represented in your model? Please choose all that apply. | E34: Pumped hydro storage;Secondary electorchemical batteries (e.g., Li-ion, etc.);Compressed air-based technologies; | F34: Secondary electorchemical batteries (e.g., Li-ion, etc.);Storage is represented as a generic or homogenous asset w/o specific technology types.;In GCAM, storage is represented generically but parameterized based on a short-duration Li-ion battery system for PV and onshore wind and molten salt thermal storage for CSP.; | G34: Flow batteries (e.g., Vanadium-Redox);Storage in the form of hydrogen; | H34: Storage is represented as a generic or homogenous asset w/o specific technology types.; | I34: Storage is represented as a generic or homogenous asset w/o specific technology types.; | J34: Secondary electorchemical batteries (e.g., Li-ion, etc.);electrolyzers + h2 turbines; | K34: No storage is modelled in TIAM-ECN. I have to give an answer to Q35 to continue the survey. ; | L34: Compressed air-based technologies;Pumped hydro storage;
C35: 1 | D35: Do you represent various storage technologies within a category (e.g., different battery chemistries) in your model? | E35: No | F35: No | G35: No | H35: No | I35: No | J35: No | K35: No | L35: No
D36: Please list technologies represented within each category mentioned above, only for applicable categories (e.g., Batteries: Li-ion, Lead-acid).
C37: 1 | D37: What technical characteristics of electricity storage are modeled explicitly? Please choose all that apply. | E37: Power capacity (MW) (used for both charge and discharge);Duration of discharge or energy-to-power ratio (h);Round-trip efficiency;Storage reservoir size (MWh);Lifetime (in years); | F37: Lifetime (in years);Replacement (partial or full);Round-trip efficiency; | G37: Our flow battery storage is included in the RLDC dataset we use. For certain shares of wind/solar, the dataset provides us with required storage capacity (MW/MWh). Round trip efficiencies are included in the dataset. Hydrogen can also be used as a way of storing electricity (although the hydrogen is not necessarily used again in het electricity sector); | H37: Capacity factor (max or nominal);Lifetime (in years);Power capacity (MW) (used for both charge and discharge);Round-trip efficiency; | I37: Capacity factor (max or nominal);Charge capacity (MW) (if it can be different from discharge capacity);Lifetime (in years);Power capacity (MW) (used for both charge and discharge); | J37: Duration of discharge or energy-to-power ratio (h);Round-trip efficiency;Storage reservoir size (MWh);Discharge capacity (MW) (if it can be different from charge capacity); | K37: No storage is modelled in TIAM-ECN; | L37: Capacity factor (max or nominal);Charge capacity (MW) (if it can be different from discharge capacity);
D38: If applicable, please list other characteristics of storage represented in your model that are not listed above: | K38: No storage is modelled in TIAM-ECN.
C39: 1 | D39: What economic characteristics of electricity storage are modeled explicitly? (O&M = operation and maintenance). Please choose all that apply. | E39: Capital cost;Fixed O&M cost; | F39: Capital cost;Variable O&M cost;Fixed O&M cost;Replacement or major retrofit cost; | G39: Capital cost; | H39: Capital cost;Variable O&M cost;Fixed O&M cost;Replacement or major retrofit cost; | I39: Capital cost;Variable O&M cost;Fixed O&M cost;End-of-lifetime cost or resale; | J39: Capital cost;Fixed O&M cost; | K39: No storage is modelled in TIAM-ECN; | L39: Capital cost;Variable O&M cost;
D40: Are the costs of the power conversion system (PCS) and the storage reservoir/container represented separately in your model? | E40: No (PCS and reservoir are treated with one cost value) | F40: No (PCS and reservoir are treated with one cost value) | G40: No (PCS and reservoir are treated with one cost value) | H40: No (PCS and reservoir are treated with one cost value) | I40: No (PCS and reservoir are treated with one cost value) | J40: No (PCS and reservoir are treated with one cost value) | K40: Cost of storage is not relevant or represented | L40: No (PCS and reservoir are treated with one cost value)
C41: 1 | D41: Which service categories are relevant for storage technologies in your model? Please tick all that apply. | E41: Energy-related (e.g., peak shaving);Power capacity-related (e.g., capacity firming);Renewable energy integration (e.g., curtailment reduction); | F41: Renewable energy integration (e.g., curtailment reduction); | G41: Renewable energy integration (e.g., curtailment reduction);Power capacity-related (e.g., capacity firming);Energy-related (e.g., peak shaving); | H41: Energy-related (e.g., peak shaving);Power capacity-related (e.g., capacity firming);T&D grid (e.g., investment deferral);Renewable energy integration (e.g., curtailment reduction);Ancillary services (e.g., frequency regulation); | I41: Renewable energy integration (e.g., curtailment reduction);Energy-related (e.g., peak shaving); | J41: Renewable energy integration (e.g., curtailment reduction); | K41: Ancillary services (e.g., frequency regulation); | L41: Power capacity-related (e.g., capacity firming);
C42: 1 | D42: Where are storage technologies represented in your model? Please tick all that apply. | E42: Storage is represented generically (no location specific); | F42: At the generation side (utility VRE); | G42: At the generation side (utility VRE);At the generation side (central power plants); | H42: At the generation side (central power plants);At the generation side (utility VRE);Power transmission level; | I42: Storage is represented generically (no location specific); | J42: Storage is represented generically (no location specific); | K42: Not relevant; | L42: At the generation side (central power plants);
C43: 1 | D43: Which energy-related storage services are represented in your model? Please tick all that apply. | E43: Energy time shifting (arbitrage);Peak shaving (e.g., daily, seasonal);Energy-related services are modeled collectively.; | F43: Energy-related services are not relevant/modeled.; | G43: Peak shaving (e.g., daily, seasonal); | H43: Energy-related services are modeled collectively.; | I43: Energy-related services are modeled collectively.; | J43: see below - not explicitly modeled; | K43: No storage is modelled in TIAM-ECN. Please ignore Q42 answer. I had to tick a box to continue the survey. ; | L43: Energy-related services are modeled collectively.;
C44: 1 | D44: Which power capacity-related storage services are represented in your model? Please tick all that apply. | E44: Back-up capacity (once or a few times a year);Capacity firming of non-VRE (e.g., day/night smoothing of nuclear power);Capacity-related services are modeled collectively.; | F44: Capacity-related services are modeled collectively.; | G44: Capacity firming of non-VRE (e.g., day/night smoothing of nuclear power); | H44: Capacity-related services are modeled collectively.; | I44: Capacity-related services are modeled collectively.; | J44: see below - not explicitly modeled; | K44: No storage is modelled in TIAM-ECN; | L44: Back-up capacity (once or a few times a year);Capacity firming of non-VRE (e.g., day/night smoothing of nuclear power);
C45: 1 | D45: Which T&D-related storage services are represented in your model? Please tick all that apply. | E45: Investment in storage has no impact on T&D.; | F45: Not relevant; | G45: Grid services are modeled collectively.; | H45: Grid services are modeled collectively.; | I45: Not relevant; | J45: Not relevant; | K45: Not relevant; | L45: Not relevant;
C46: 1 | D46: Which storage services concerning VRE are represented in your model? Please tick all that apply. | E46: VRE-related services of storage are modeled in an aggregated way (i.e., no individual representation of services).;Curtailment reduction;Energy time-shifting;Short-term flexibility/balancing (operative reserve);Capacity firming (increasing capacity value of VRE); | F46: Curtailment reduction;Integration cost reduction;VRE-related services of storage are modeled in an aggregated way (i.e., no individual representation of services).; | G46: Curtailment reduction;Capacity firming (increasing capacity value of VRE); | H46: Curtailment reduction;Integration cost reduction;Short-term flexibility/balancing (operative reserve);Capacity firming (increasing capacity value of VRE); | I46: Curtailment reduction;Energy time-shifting; | J46: VRE-related services of storage are modeled in an aggregated way (i.e., no individual representation of services).; | K46: No storage is modelled in TIAM-ECN; | L46: Curtailment reduction;
D47: Please briefly explain the way energy storage can support the integration of VRE in your model, if not fully covered through the questions asked above. | E47: Potentially, energy storage in our model could provide the services ticked in Q.44, Q.45, and Q.47, however, these are not modeled as explicit, disaggregated services. Rather, in our model, energy storage is represented only as a device that can charge and discharge energy within the optimization of power system operation, and it is only ex post that storage is interpreted as having provided such services. | F47: For variable renewable energy technologies (e.g., PV, CSP, onshore wind), GCAM represents two technology options: (1) VRE without dedicated storage which is subject to integration costs (reduced value factor with increasing market share) or (2) VRE with dedicated storage (short-duration Li-ion battery for PV and onshore wind; molten salt thermal storage for CSP) which entail additional capital and O&M costs and round trip energy losses but do not face any integration costs. | J47: Storage deployment is modeled as a requirement from VRE deployment, with the specific storage requirements per kWh of VRE electricity increasing linearly with the share of VRE. (so in total, storage requirements increase roughly with the square of VRE share)
C48: 1 | D48: Which one of the following parameters affects the deployment of energy storage technologies in your model positively? Please tick all that apply. | E48: Cost competetiveness (incl. capital cost, O&M cost, levelized cost, etc.) compared to other alternatives;Considering the duration of storage services (short vs. long duration);Rapid cost learning, i.e., the decline of storage cost in future;The increasing share of VRE in the system (e.g., as % of annual load or generation);The value of capacity services of storage;Barriers in the deployment of competing technologies (e.g., demand response, grid expansion, etc.);Increased volatility in the pattern of electric load within a year;Increased variability in the pattern of VRE within a year; | F48: Cost competetiveness (incl. capital cost, O&M cost, levelized cost, etc.) compared to other alternatives;The increasing share of VRE in the system (e.g., as % of annual load or generation); | G48: The increasing share of VRE in the system (e.g., as % of annual load or generation); | H48: Cost competetiveness (incl. capital cost, O&M cost, levelized cost, etc.) compared to other alternatives;Rapid cost learning, i.e., the decline of storage cost in future;The increasing share of VRE in the system (e.g., as % of annual load or generation);The value of capacity services of storage;Barriers in the deployment of competing technologies (e.g., demand response, grid expansion, etc.);Considering the duration of storage services (short vs. long duration); | I48: Cost competetiveness (incl. capital cost, O&M cost, levelized cost, etc.) compared to other alternatives;Rapid cost learning, i.e., the decline of storage cost in future;The increasing share of VRE in the system (e.g., as % of annual load or generation);The value of capacity services of storage;Increased variability in the pattern of VRE within a year; | J48: The increasing share of VRE in the system (e.g., as % of annual load or generation); | K48: Not relevant; | L48: Cost competetiveness (incl. capital cost, O&M cost, levelized cost, etc.) compared to other alternatives;Rapid cost learning, i.e., the decline of storage cost in future;The increasing share of VRE in the system (e.g., as % of annual load or generation);
D49: Please explain if the answer included "Other" and/or if you would like to add explanations.
C50: 1 | D50: How is the system integration of electricity storage constrained in your model? Please tick all that apply. | E50: (Some or all) storage technologies are constrained by available sites, resource potential, material availability, etc. (i.e., static constraints not necessarily dependent on storage deployment); | F50: Storage capacity/activity is dependent to that of VRE (i.e., no VRE --> no storage).; | G50: The RLDC dataset we use includes required storage capacity for different shares of VRE; | H50: Storage can be deployed in competition with other alternatives, without any specific limit.;Storage is constrained by build-up, technological learning, and/or market-penetration growth rates (i.e., dynamic constraints dependent on storage deployment).; | I50: Storage capacity/activity is dependent to that of VRE (i.e., no VRE --> no storage).; | J50: Storage capacity/activity is dependent to that of VRE (i.e., no VRE --> no storage).;Storage is constrained by build-up, technological learning, and/or market-penetration growth rates (i.e., dynamic constraints dependent on storage deployment).; | K50: Not relevant; | L50: Storage capacity/activity is dependent to that of VRE (i.e., no VRE --> no storage).;Storage capacity/activity is capped to a certain share of another process, such as generation, flexibility, T&D, load, etc. (e.g., max 40% of load can be met by storage discharge);
C51: 1 | D51: Can storage technologies contribute to multiple services in your model? This functionality known as "revenue stacking" or "aggregation of benefits" allows a storage provider to offer energy-, cap... | E51: Yes, storage can provide multiple services without any limits. | F51: Not relevant | G51: No, the contribution of storage is only allowed to certain services (e.g., either to energy- or capacity-related services). | H51: Yes, storage can provide multiple services without any limits. | I51: Not relevant | J51: as said above, storage is directly hard-linked to VRE deployment | K51: Not relevant | L51: No, the contribution of storage is only allowed to certain services (e.g., either to energy- or capacity-related services).
C52: 1 | D52: How is the ownership of storage and its revenues represented in your model? | E52: Storage contributes to the system-level benefits. | F52: Depending on the location of storage, it can be owned by the grid, energy utilites, or end user, and would benefit the respective owner. | G52: Storage contributes to the system-level benefits. | H52: Storage contributes to the system-level benefits. | I52: Not relevant | J52: Not relevant | K52: Not relevant | L52: Storage contributes to the system-level benefits.
D53: Please add any points related to the integration of energy storage in your model that you believe are not covered in the previous questions.
C54: 1 | D54: Are energy storage technologies and their parameters treated differently based on the modeled scenario in your work? (e.g., more optimistic energy storage cost assumptions in electrification scena... | E54: No, storage parameters were kept consistently across scenarios. | F54: Yes | G54: Yes | H54: No, storage parameters were kept consistently across scenarios. | I54: Yes | J54: Yes | K54: No, storage parameters were kept consistently across scenarios. | L54: No, storage parameters were kept consistently across scenarios.
D55: If relevant, please explain your scenario-specific assumptions concerning storage technologies briefly. For example, do you consider different storage performance/cost parameters or storage integr... | E55: In our model, the techno-economic parameters of storage technologies are basically kept identical across scenarios. | F55: I am not personally involved in ECEMF and am not aware of GCAM involvement. I answered Yes to question 49 since N/A was not an option. GCAM does include central, high, and low cost storage assumptions that can be used in different scenarios. | G55: The RLDC dataset (including storage) is available for various levels of VRE integration constraints (strict, normal, relaxed) | H55: N/A | I55: yes | J55: yes, we decrease the storage capacity requirements at a given VRE share, as we assume more demand side management, better use of vehicle-to-grid, better pooling etc. | K55: No storage is modelled in TIAM-ECN. | L55: for now we didnt change storage parameters.
D56: (Only for the teams in the ECEMF project) We need additional variables for conducting the storage analysis. Please tick all Priority 1 variables that you can report for your scenarios. | E56: Not participated in ECEMF; | F56: Not participated in ECEMF; | G56: Capacity of storage (GWh);Electricity supplied/discharged by storage technologies (EJ/yr);Power capacity of electricity storage (GW);Power capacity of hydrogen electrolyzer (GW); | H56: Capacity of storage (GWh);Capital cost of storage technologies (EUR/GW or EUR/GWh);Efficiency of storage technologies (as % or lost energy (EJ/yr));Lifetime of storage technologies (year);Net electricity trade (import/export) (EJ/yr);Power capacity of electricity storage (GW);Power capacity of hydrogen electrolyzer (GW); | I56: Capacity of storage (GWh);Capital cost of storage technologies (EUR/GW or EUR/GWh); | J56: Capacity of storage (GWh);Capital cost of storage technologies (EUR/GW or EUR/GWh);Duration of charge/discharge (h);Power capacity of electricity storage (GW);Power capacity of hydrogen electrolyzer (GW); | K56: Power capacity of hydrogen electrolyzer (GW);Net electricity trade (import/export) (EJ/yr); | L56: Capacity of storage (GWh);Lifetime of storage technologies (year);Power capacity of electricity storage (GW);

Sheet SRF-detailed
A1: SRF Dimension | B1: Sub-dimension | C1: Indicator | D1: Sub-indicator | E1: AIM-T | F1: GCAM | G1: IMAGE | H1: MESSAGEix-GLOBIOM | I1: PROMETHEUS | J1: REMIND | K1: TIAM-ECN | L1: WITCH | M1: Max | N1: Notes
A2: Storage representation (SRF) | B2: Storage technology | C2: Storage modelled explicitly | D2: Explicit | E2: 1 | F2: 1 | G2: 0.5 | H2: 1 | I2: 1 | J2: 1 | K2: Not modelled | L2: 1 | M2: 1 | N2: In response to Question 36 (yes=1, implicit=0.5, No=0)
A4: Storage representation (SRF) | B4: Storage technology | C4: Short and long-duration storage represented | D4: Sub-total | E4: 1 | F4: 0.5 | G4: 1 | H4: 1 | I4: 1 | J4: 1 | K4: 0 | L4: 1 | M4: 1 | N4: In response to Question 37 (short=0.5, long=0.5)
A5: Storage representation (SRF) | B5: Storage technology | C5: Short and long-duration storage represented | D5: Short-duration | E5: ✓ | F5: — | G5: ✓ | H5: ✓ | I5: ✓ | J5: ✓ | K5: N/A | L5: ✓ | M5: 0.5
A6: Storage representation (SRF) | B6: Storage technology | C6: Short and long-duration storage represented | D6: Long-duration | E6: ✓ | F6: ✓ | G6: ✓ | H6: ✓ | I6: ✓ | J6: ✓ | K6: N/A | L6: ✓ | M6: 0.5
A8: Storage representation (SRF) | B8: Storage technology | C8: Storage technologies represented | D8: Sub-total | E8: 1 | F8: 0.75 | G8: 0.5 | H8: 0.75 | I8: 0.75 | J8: 0.5 | K8: 0 | L8: 0.75 | M8: 1.25 | N8: In response to Question 38 (0.25 per key (near-)commercial technology (PHS, CAES, Batteries, flow batteries, hydrogen), 0.5 = generic, max = 1.25). Note: hydrogen has been taken into account for those who missed reporting here, but reported elsewhere. Generic is only considered once for each duration (e.g., a model cannot add up generic and batteries at the same time for short-duration storage, but they can add up generic for short-term with hydrogen for long-term).
A9: Storage representation (SRF) | B9: Storage technology | C9: Storage technologies represented | D9: Batteries (electrochemical) | E9: ✓ | F9: — | G9: — | H9: — | I9: — | J9: ✓ | K9: N/A | L9: ✓ | M9: 0.25
A10: Storage representation (SRF) | B10: Storage technology | C10: Storage technologies represented | D10: Compressed air | E10: ✓ | F10: — | G10: — | H10: — | I10: — | J10: — | K10: N/A | L10: ✓ | M10: 0.25
A11: Storage representation (SRF) | B11: Storage technology | C11: Storage technologies represented | D11: Flow batteries | E11: — | F11: — | G11: (✓) | H11: — | I11: — | J11: — | K11: N/A | M11: 0.25
A12: Storage representation (SRF) | B12: Storage technology | C12: Storage technologies represented | D12: Generic | E12: — | F12: ✓ | G12: — | H12: ✓ | I12: ✓ | J12: — | K12: N/A | M12: 0.5
A13: Storage representation (SRF) | B13: Storage technology | C13: Storage technologies represented | D13: Hydrogen | E13: ✓ | F13: ✓ | G13: ✓ | H13: ✓ | I13: ✓ | J13: ✓ | K13: N/A | L13: ✓ | M13: 0.25
A14: Storage representation (SRF) | B14: Storage technology | C14: Storage technologies represented | D14: Pumped hydro | E14: ✓ | F14: — | G14: — | H14: — | I14: — | J14: — | K14: N/A | L14: — | M14: 0.25
A16: Storage representation (SRF) | B16: Storage technology | C16: Storage technology sub-classes (e.g., Li-ion, Sodium-ion etc.) | D16: Storage technology | E16: 0 | F16: 0 | G16: 0 | H16: 0 | I16: 0 | J16: 0 | K16: N/A | L16: 0 | M16: 1 | N16: In response to Question 39 (0=no, 0.5=Med (a few), 1=High (all technologies))
A18: Storage representation (SRF) | B18: Storage parameters | C18: Technical representation | D18: Subtotal | E18: 1 | F18: 0.75 | G18: 0.25 | H18: 1 | I18: 1 | J18: 1.5 | K18: 0 | L18: 0.5 | M18: =SUM(M19:M32) -> 3.5
A19: Storage representation (SRF) | B19: Storage parameters | C19: Technical representation | D19: Capacity factor | E19: — | F19: — | G19: — | H19: ✓ | I19: ✓ | J19: — | K19: N/A | L19: ✓ | M19: 0.25 | N19: In response to Q41 ( 0.25 per parameter, max=14*0.25=3.5).
A20: Storage representation (SRF) | B20: Storage parameters | C20: Technical representation | D20: Charging/discharge capacity separately | E20: — | F20: — | G20: — | H20: — | I20: ✓ | J20: ✓ | K20: N/A | L20: ✓ | M20: 0.25
A21: Storage representation (SRF) | B21: Storage parameters | C21: Technical representation | D21: Degradation due to operating cycles | E21: — | F21: — | G21: — | H21: — | I21: — | J21: — | K21: N/A | L21: — | M21: 0.25
A22: Storage representation (SRF) | B22: Storage parameters | C22: Technical representation | D22: Depth of discharge | E22: — | F22: — | G22: — | H22: — | I22: — | J22: — | K22: N/A | L22: — | M22: 0.25
A23: Storage representation (SRF) | B23: Storage parameters | C23: Technical representation | D23: Duration of discharge (energy to power ratio) (h) | E23: — | F23: — | G23: — | H23: — | I23: — | J23: ✓ | K23: N/A | L23: — | M23: 0.25
A24: Storage representation (SRF) | B24: Storage parameters | C24: Technical representation | D24: Efficiency (roundtrip) | E24: ✓ | F24: ✓ | G24: — | H24: ✓ | I24: — | J24: ✓ | K24: N/A | L24: — | M24: 0.25
A25: Storage representation (SRF) | B25: Storage parameters | C25: Technical representation | D25: Efficiency charge/discharge separately | E25: — | F25: — | G25: — | H25: — | I25: — | J25: — | K25: N/A | L25: — | M25: 0.25
A26: Storage representation (SRF) | B26: Storage parameters | C26: Technical representation | D26: Lifetime (years or cycles) | E26: ✓ | F26: ✓ | G26: — | H26: ✓ | I26: ✓ | J26: ✓ | K26: N/A | L26: — | M26: 0.25
A27: Storage representation (SRF) | B27: Storage parameters | C27: Technical representation | D27: Power capacity (overall) | E27: ✓ | F27: — | G27: ✓ | H27: ✓ | I27: ✓ | J27: ✓ | K27: N/A | L27: — | M27: 0.25
A28: Storage representation (SRF) | B28: Storage parameters | C28: Technical representation | D28: Replacement | E28: ✓ | F28: ✓ | G28: — | H28: — | I28: — | J28: — | K28: N/A | L28: — | M28: 0.25
A29: Storage representation (SRF) | B29: Storage parameters | C29: Technical representation | D29: State of charge (SoC) | E29: — | F29: — | G29: — | H29: — | I29: — | J29: — | K29: N/A | L29: — | M29: 0.25
A30: Storage representation (SRF) | B30: Storage parameters | C30: Technical representation | D30: Storage balance (match start and end content within a year) | E30: — | F30: — | G30: — | H30: — | I30: — | J30: — | K30: N/A | L30: — | M30: 0.25
A31: Storage representation (SRF) | B31: Storage parameters | C31: Technical representation | D31: Storage self-discharge (in the idle mode) | E31: — | F31: — | G31: — | H31: — | I31: — | J31: — | K31: N/A | L31: — | M31: 0.25
A32: Storage representation (SRF) | B32: Storage parameters | C32: Technical representation | D32: Storage reservoir size (MWh) | E32: — | F32: — | G32: — | H32: — | I32: — | J32: ✓ | K32: N/A | L32: — | M32: 0.25
A34: Storage representation (SRF) | B34: Storage parameters | C34: Economic parameters | D34: Subtotal | E34: 0.75 | F34: 1 | G34: 0.25 | H34: 0.75 | I34: 1 | J34: 0.5 | K34: N/A | L34: 0.5 | M34: =SUM(M35:M40) -> 1.5 | N34: In response to Q43 ( 0.25 per parameter, max=6*0.25=1.5).
A35: Storage representation (SRF) | B35: Storage parameters | C35: Economic parameters | D35: Capital cost | E35: ✓ | F35: ✓ | G35: ✓ | H35: ✓ | I35: ✓ | J35: ✓ | K35: N/A | L35: ✓ | M35: 0.25
A36: Storage representation (SRF) | B36: Storage parameters | C36: Economic parameters | D36: Cost of storage is not relevant or not represented | E36: — | F36: — | G36: — | H36: — | I36: — | J36: — | K36: N/A | L36: — | M36: 0.25
A37: Storage representation (SRF) | B37: Storage parameters | C37: Economic parameters | D37: End-of-lifetime cost or resale | E37: — | F37: — | G37: — | H37: — | I37: ✓ | J37: — | K37: N/A | L37: — | M37: 0.25
A38: Storage representation (SRF) | B38: Storage parameters | C38: Economic parameters | D38: Fixed O&M cost | E38: ✓ | F38: ✓ | G38: — | H38: ✓ | I38: ✓ | J38: ✓ | K38: N/A | L38: — | M38: 0.25
A39: Storage representation (SRF) | B39: Storage parameters | C39: Economic parameters | D39: Replacement or major retrofit cost | E39: ✓ | F39: ✓ | G39: — | H39: — | I39: — | J39: — | K39: N/A | L39: — | M39: 0.25
A40: Storage representation (SRF) | B40: Storage parameters | C40: Economic parameters | D40: Variable O&M cost | E40: — | F40: ✓ | G40: — | H40: ✓ | I40: ✓ | J40: — | K40: N/A | L40: ✓ | M40: 0.25
A42: Storage representation (SRF) | B42: Storage services | C42: Storage energy services details (not including VRE curtailment) | D42: Sub-total | E42: 0.5 | F42: 0 | G42: 0.25 | H42: 0.5 | I42: 0.5 | J42: 0 | K42: 0 | L42: 0.5 | M42: 1 | N42: In response to Q47 (collective: 0.5, or individual services: 0.25 per service, max=4*0.25=1). If "Collective" is ticked, it cannot be added to the scores of individual services.
A43: Storage representation (SRF) | B43: Storage services | C43: Storage energy services details (not including VRE curtailment) | D43: Arbitrage | E43: ✓ | F43: — | G43: — | H43: — | I43: — | J43: — | K43: N/A | L43: — | M43: 0.25
A44: Storage representation (SRF) | B44: Storage services | C44: Storage energy services details (not including VRE curtailment) | D44: Collective | E44: ✓ | F44: — | G44: — | H44: ✓ | I44: ✓ | J44: — | K44: N/A | L44: ✓ | M44: 0.5
A45: Storage representation (SRF) | B45: Storage services | C45: Storage energy services details (not including VRE curtailment) | D45: Fuel supply firming | E45: — | F45: — | G45: — | H45: — | I45: — | J45: — | K45: N/A | L45: — | M45: 0.25
A46: Storage representation (SRF) | B46: Storage services | C46: Storage energy services details (not including VRE curtailment) | D46: Peak shaving | E46: ✓ | F46: — | G46: ✓ | H46: — | I46: — | J46: — | K46: N/A | L46: — | M46: 0.25
A47: Storage representation (SRF) | B47: Storage services | C47: Storage energy services details (not including VRE curtailment) | D47: Self-consumption end user | E47: — | F47: — | G47: — | H47: — | I47: — | J47: — | K47: N/A | L47: — | M47: 0.25
A49: Storage representation (SRF) | B49: Storage services | C49: Storage power/ancillary services | D49: Sub-total | E49: 0.5 | F49: 0.5 | G49: 0.25 | H49: 0.5 | I49: 0.5 | J49: 0 | K49: 0 | L49: 0.5 | M49: 1 | N49: In response to Q48 (collective: 0.5, individual services: 0.25, max=4*0.25=1). If "Collective" is ticked, it cannot be added to the scores of individual services.
A50: Storage representation (SRF) | B50: Storage services | C50: Storage power/ancillary services | D50: Backup | E50: ✓ | F50: — | G50: — | H50: — | I50: — | J50: — | K50: N/A | L50: ✓ | M50: 0.25
A51: Storage representation (SRF) | B51: Storage services | C51: Storage power/ancillary services | D51: Collective | E51: ✓ | F51: ✓ | G51: — | H51: ✓ | I51: ✓ | J51: — | K51: N/A | L51: — | M51: 0.5
A52: Storage representation (SRF) | B52: Storage services | C52: Storage power/ancillary services | D52: Firming non-VRE | E52: ✓ | F52: — | G52: ✓ | H52: — | I52: — | J52: — | K52: N/A | L52: ✓ | M52: 0.25
A53: Storage representation (SRF) | B53: Storage services | C53: Storage power/ancillary services | D53: Frequency regulation (primary, secondary, and tertiary) | E53: — | F53: — | G53: — | H53: — | I53: — | J53: — | K53: N/A | L53: — | M53: 0.25
A54: Storage representation (SRF) | B54: Storage services | C54: Storage power/ancillary services | D54: Power quality services (end use) | E54: — | F54: — | G54: — | H54: — | I54: — | J54: — | K54: N/A | L54: — | M54: 0.25
A56: Storage representation (SRF) | B56: Storage services | C56: Storage T&D services | D56: Sub-total | E56: 0 | F56: 0 | G56: 0.5 | H56: 0.5 | I56: 0 | J56: 0 | K56: 0 | L56: 0 | M56: 0.75 | N56: In response to Q49 (collective: 0.5, individual services: 0.25, max=3*0.25=0.75). If "Collective" is ticked, it cannot be added to the scores of individual services.
A57: Storage representation (SRF) | B57: Storage services | C57: Storage T&D services | D57: Collective | E57: — | F57: — | G57: ✓ | H57: ✓ | I57: — | J57: — | K57: N/A | L57: — | M57: 0.5
A58: Storage representation (SRF) | B58: Storage services | C58: Storage T&D services | D58: Congestion relief | E58: — | F58: — | G58: — | H58: — | I58: — | J58: — | K58: N/A | L58: — | M58: 0.25
A59: Storage representation (SRF) | B59: Storage services | C59: Storage T&D services | D59: Investment deferral | E59: — | F59: — | G59: — | H59: — | I59: — | J59: — | K59: N/A | L59: — | M59: 0.25
A60: Storage representation (SRF) | B60: Storage services | C60: Storage T&D services | D60: T&D modelled separately | E60: — | F60: — | G60: — | H60: — | I60: — | J60: — | K60: N/A | L60: — | M60: 0.25
A62: Storage representation (SRF) | B62: Storage services | C62: Storage VRE integration services | D62: Sub-total | E62: 1 | F62: 0.5 | G62: 0.5 | H62: 1 | I62: 0.5 | J62: 0.5 | K62: 0 | L62: 0.25 | M62: 1.5 | N62: In response to Q50 (collective: 0.5, individual services: 0.25, max=6*0.25=1.5). If "Collective" is ticked, it cannot be added to the scores of individual services.
A63: Storage representation (SRF) | B63: Storage services | C63: Storage VRE integration services | D63: Collective | E63: — | F63: ✓ | G63: — | H63: — | I63: — | J63: ✓ | K63: N/A | L63: — | M63: 0.5
A64: Storage representation (SRF) | B64: Storage services | C64: Storage VRE integration services | D64: Curtailment reduction | E64: ✓ | F64: ✓ | G64: ✓ | H64: ✓ | I64: ✓ | J64: — | K64: N/A | L64: ✓ | M64: 0.25
A65: Storage representation (SRF) | B65: Storage services | C65: Storage VRE integration services | D65: Firming capacity | E65: ✓ | F65: — | G65: ✓ | H65: ✓ | I65: — | J65: — | K65: N/A | L65: — | M65: 0.25
A66: Storage representation (SRF) | B66: Storage services | C66: Storage VRE integration services | D66: Integration cost reducing | E66: — | F66: ✓ | G66: — | H66: ✓ | I66: — | J66: — | K66: N/A | L66: — | M66: 0.25
A67: Storage representation (SRF) | B67: Storage services | C67: Storage VRE integration services | D67: Operating reserve (balancing) | E67: ✓ | F67: — | G67: — | H67: ✓ | I67: — | J67: — | K67: N/A | L67: — | M67: 0.25
A68: Storage representation (SRF) | B68: Storage services | C68: Storage VRE integration services | D68: Time-shifting | E68: ✓ | F68: — | G68: — | H68: — | I68: ✓ | J68: — | K68: N/A | L68: — | M68: 0.25
A69: Storage representation (SRF) | B69: Storage services | C69: Storage VRE integration services | D69: Self-consumption (end use) | E69: — | F69: — | G69: — | H69: — | I69: — | J69: — | K69: N/A | L69: — | M69: 0.25
A71: Storage representation (SRF) | B71: Storage services | C71: Storage multi-tasking (aggregation of benefits) | D71: Sub-total | E71: 0.75 | F71: 0 | G71: 0 | H71: 0.75 | I71: 0 | J71: 0.25 | K71: 0 | L71: 0 | M71: 1 | N71: In response to Q55 (not allowed or not relevant=0, limited to certain services =0.25, Multiple, maximising storage value=0.5, Multiple, flexible=0.75, Multiple, with an allocation model=1) Note 1: storage maximising benefits from multiple services is scored 0.5, because that may not be consistent with the system value (not desirable from system-perspective); Note 2: Storage with allocation model is scored higher than "no limit" in multi-tasking, as no limit may overestimate the availability of storage for providing multiple services at peak demand times.
A72: Storage representation (SRF) | B72: Storage services | C72: Storage multi-tasking (aggregation of benefits) | D72: No, not allowed | E72: — | F72: — | G72: ✓ | H72: — | I72: — | J72: — | K72: N/A | L72: ✓ | M72: 0
A73: Storage representation (SRF) | B73: Storage services | C73: Storage multi-tasking (aggregation of benefits) | D73: No, storage is directly hard-linked to VRE deployment | E73: — | F73: — | G73: — | H73: — | I73: — | J73: ✓ | K73: N/A | L73: — | M73: 0.25
A74: Storage representation (SRF) | B74: Storage services | C74: Storage multi-tasking (aggregation of benefits) | D74: Yes, maximising storage value | E74: — | F74: — | G74: — | H74: — | I74: — | J74: — | K74: N/A | L74: — | M74: 0.5
A75: Storage representation (SRF) | B75: Storage services | C75: Storage multi-tasking (aggregation of benefits) | D75: Yes, with no limit | E75: ✓ | F75: — | G75: — | H75: ✓ | I75: — | J75: — | K75: N/A | L75: — | M75: 0.75
A76: Storage representation (SRF) | B76: Storage services | C76: Storage multi-tasking (aggregation of benefits) | D76: Yes, with an allocation model | E76: — | F76: — | G76: — | H76: — | I76: — | J76: — | K76: N/A | L76: — | M76: 1
A78: Storage representation (SRF) | B78: Storage integration | C78: Storage uptake parameterisation | D78: Sub-total | E78: 2 | F78: 0.5 | G78: 0.25 | H78: 1.5 | I78: 1.25 | J78: 1 | K78: 0 | L78: 0.75 | M78: 2.25 | N78: In response to Q52 (individual parameters: 0.25, max=9*0.25=2.25), Rationale: the more explicit parameterisation of storage is scored higher.
A79: Storage representation (SRF) | B79: Storage integration | C79: Storage uptake parameterisation | D79: Ancillary services | E79: — | F79: — | G79: — | H79: — | I79: — | J79: — | K79: N/A | L79: — | M79: 0.25
A80: Storage representation (SRF) | B80: Storage integration | C80: Storage uptake parameterisation | D80: Capacity value | E80: ✓ | F80: — | G80: — | H80: ✓ | I80: ✓ | J80: — | K80: N/A | L80: — | M80: 0.25
A81: Storage representation (SRF) | B81: Storage integration | C81: Storage uptake parameterisation | D81: Cost | E81: ✓ | F81: ✓ | G81: — | H81: ✓ | I81: ✓ | J81: ✓ | K81: N/A | L81: ✓ | M81: 0.25
A82: Storage representation (SRF) | B82: Storage integration | C82: Storage uptake parameterisation | D82: Duration | E82: ✓ | F82: — | G82: — | H82: ✓ | I82: — | J82: — | K82: N/A | L82: — | M82: 0.25
A83: Storage representation (SRF) | B83: Storage integration | C83: Storage uptake parameterisation | D83: Learning rate | E83: ✓ | F83: — | G83: — | H83: ✓ | I83: ✓ | J83: ✓ | K83: N/A | L83: ✓ | M83: 0.25
A84: Storage representation (SRF) | B84: Storage integration | C84: Storage uptake parameterisation | D84: Limited alternatives | E84: ✓ | F84: — | G84: — | H84: ✓ | I84: — | J84: — | K84: N/A | L84: — | M84: 0.25
A85: Storage representation (SRF) | B85: Storage integration | C85: Storage uptake parameterisation | D85: Load variability | E85: ✓ | F85: — | G85: — | H85: — | I85: — | J85: — | K85: N/A | L85: — | M85: 0.25
A86: Storage representation (SRF) | B86: Storage integration | C86: Storage uptake parameterisation | D86: VRE share in the system | E86: ✓ | F86: ✓ | G86: ✓ | H86: ✓ | I86: ✓ | J86: ✓ | K86: N/A | L86: ✓ | M86: 0.25
A87: Storage representation (SRF) | B87: Storage integration | C87: Storage uptake parameterisation | D87: VRE variability | E87: ✓ | F87: — | G87: — | H87: — | I87: ✓ | J87: ✓ | K87: N/A | L87: — | M87: 0.25
A89: Storage representation (SRF) | B89: Storage integration | C89: Storage deployment constraints | D89: Sub-total | E89: 0.25 | F89: 0.25 | G89: 0.25 | H89: 0.75 | I89: 0.25 | J89: 0.5 | K89: 0 | L89: 0.25 | M89: 1.25 | N89: In response to Q54 (not explicit=0, three limiting parameters each 0.25, two enabling constraints each 0.5: 3 * 0.25 + 1 * 0.5 = 1.25 max), Rationale: Limiting constraints on the uptake of storage are scored lower, while enabling, flexible uptake is scored higher. Hard constraints cannot be added to other constraints.
A90: Storage representation (SRF) | B90: Storage integration | C90: Storage deployment constraints | D90: Dynmaic constraints (learning) | E90: — | F90: — | G90: — | H90: ✓ | I90: — | J90: ✓ | K90: N/A | L90: — | M90: 0.25
A91: Storage representation (SRF) | B91: Storage integration | C91: Storage deployment constraints | D91: Hard constraints on storage | E91: — | F91: — | G91: — | H91: — | I91: — | J91: — | K91: N/A | L91: ✓ | M91: 0.25
A92: Storage representation (SRF) | B92: Storage integration | C92: Storage deployment constraints | D92: Input constraints (sites, potential, materials, etc.) | E92: ✓ | F92: — | G92: — | H92: — | I92: — | J92: — | K92: N/A | L92: — | M92: 0.25
A93: Storage representation (SRF) | B93: Storage integration | C93: Storage deployment constraints | D93: No limit compared to alternatives | E93: — | F93: — | G93: — | H93: ✓ | I93: — | J93: — | K93: N/A | L93: — | M93: 0.5
A94: Storage representation (SRF) | B94: Storage integration | C94: Storage deployment constraints | D94: VRE-dependent | E94: — | F94: ✓ | G94: ✓ | H94: — | I94: ✓ | J94: ✓ | K94: N/A | L94: ✓ | M94: 0.25
A96: Storage representation (SRF) | B96: Storage parameters | C96: Storage parameters dependent on the scenario | D96: Sub-total | E96: 0 | F96: 0.5 | G96: 0.5 | H96: 0 | I96: 0.5 | J96: 0.5 | K96: 0 | L96: 0 | M96: 0.5 | N96: In response to Q58: No=0, Yes=0.5
A97: Storage representation (SRF) | B97: Storage parameters | C97: Storage parameters dependent on the scenario | D97: Yes | E97: — | F97: ✓ | G97: ✓ | H97: — | I97: ✓ | J97: ✓ | K97: N/A | L97: — | M97: 0.5
A99: Storage representation (SRF) | D99: Dimension-total | E99: =E96+E89+E78+E71+E62+E56+E49+E42+E16+E8+E4+E2+E34+E18 -> 9.75 | F99: =F96+F89+F78+F71+F62+F56+F49+F42+F16+F8+F4+F2+F34+F18 -> 6.25 | G99: =G96+G89+G78+G71+G62+G56+G49+G42+G16+G8+G4+G2+G34+G18 -> 5 | H99: =H96+H89+H78+H71+H62+H56+H49+H42+H16+H8+H4+H2+H34+H18 -> 10 | I99: =I96+I89+I78+I71+I62+I56+I49+I42+I16+I8+I4+I2+I34+I18 -> 8.25 | J99: =J96+J89+J78+J71+J62+J56+J49+J42+J16+J8+J4+J2+J34+J18 -> 7.25 | K99: 0 | L99: =L96+L89+L78+L71+L62+L56+L49+L42+L16+L8+L4+L2+L34+L18 -> 6 | M99: =M96+M89+M78+M71+M62+M56+M49+M42+M16+M8+M4+M2+M34+M18 -> 18.5
A101: VRE integration (SRF) | B101: VRE technology | C101: VRE technologies modelled | D101: Sub-total | E101: 1.25 | F101: 1 | G101: 1.75 | H101: 1 | I101: 1 | J101: 1.25 | K101: 1.25 | L101: 1 | M101: 1.75 | N101: In response to Q28 (max 8 items, 0.25 point per item). Note: Solar PV (general) cannot be added to the rooftop or utility if reported separately.
A102: VRE integration (SRF) | B102: VRE technology | C102: VRE technologies modelled | D102: Concentrated solar power (CSP) | E102: ✓ | F102: ✓ | G102: ✓ | H102: ✓ | I102: ✓ | J102: ✓ | K102: ✓ | L102: ✓ | M102: 0.25
A103: VRE integration (SRF) | B103: VRE technology | C103: VRE technologies modelled | D103: Offshore wind | E103: ✓ | F103: ✓ | G103: ✓ | H103: ✓ | I103: ✓ | J103: ✓ | K103: ✓ | L103: ✓ | M103: 0.25
A104: VRE integration (SRF) | B104: VRE technology | C104: VRE technologies modelled | D104: Onshore wind | E104: ✓ | F104: ✓ | G104: ✓ | H104: ✓ | I104: ✓ | J104: ✓ | K104: ✓ | L104: ✓ | M104: 0.25
A105: VRE integration (SRF) | B105: VRE technology | C105: VRE technologies modelled | D105: Riverhydro | E105: — | F105: — | G105: ✓ | H105: — | I105: — | J105: ✓ | K105: ✓ | L105: — | M105: 0.25
A106: VRE integration (SRF) | B106: VRE technology | C106: VRE technologies modelled | D106: Tidal/wave power | E106: — | F106: — | G106: ✓ | H106: — | I106: — | J106: — | K106: — | L106: — | M106: 0.25
A107: VRE integration (SRF) | B107: VRE technology | C107: VRE technologies modelled | D107: Solar PV (general) | E107: — | F107: — | G107: ✓ | H107: ✓ | I107: ✓ | J107: ✓ | K107: ✓ | L107: ✓ | M107: 0.25
A108: VRE integration (SRF) | B108: VRE technology | C108: VRE technologies modelled | D108: Solar PV (rooftop) | E108: ✓ | F108: ✓ | G108: ✓ | H108: — | I108: — | J108: — | K108: — | L108: — | M108: 0.25
A109: VRE integration (SRF) | B109: VRE technology | C109: VRE technologies modelled | D109: Solar PV (utility) | E109: ✓ | F109: ✓ | G109: ✓ | H109: — | I109: — | J109: — | K109: — | L109: — | M109: 0.25
A111: VRE integration (SRF) | B111: VRE parameters | C111: VRE characteristics modelled | D111: Sub-total | E111: 1.5 | F111: 1 | G111: 1.75 | H111: 1.5 | I111: 1.25 | J111: 1.25 | K111: 1.25 | L111: 1.25 | M111: 2 | N111: In response to Q29 (max 8 items, 0.25 point per item)
A112: VRE integration (SRF) | B112: VRE parameters | C112: VRE characteristics modelled | D112: Capacity value | E112: ✓ | F112: — | G112: ✓ | H112: ✓ | I112: — | J112: — | K112: — | L112: ✓ | M112: 0.25
A113: VRE integration (SRF) | B113: VRE parameters | C113: VRE characteristics modelled | D113: Cost (direct) | E113: ✓ | F113: ✓ | G113: ✓ | H113: ✓ | I113: ✓ | J113: ✓ | K113: ✓ | L113: ✓ | M113: 0.25
A114: VRE integration (SRF) | B114: VRE parameters | C114: VRE characteristics modelled | D114: Curtailment | E114: ✓ | F114: — | G114: ✓ | H114: ✓ | I114: — | J114: ✓ | K114: — | L114: ✓ | M114: 0.25
A115: VRE integration (SRF) | B115: VRE parameters | C115: VRE characteristics modelled | D115: Integration cost | E115: — | F115: ✓ | G115: ✓ | H115: ✓ | I115: ✓ | J115: ✓ | K115: ✓ | L115: ✓ | M115: 0.25
A116: VRE integration (SRF) | B116: VRE parameters | C116: VRE characteristics modelled | D116: Resource potential | E116: ✓ | F116: ✓ | G116: ✓ | H116: ✓ | I116: ✓ | J116: ✓ | K116: ✓ | L116: ✓ | M116: 0.25
...

Sheet SRF-total
A1: Total | B1: AIM-T | C1: GCAM | D1: IMAGE | E1: MESSAGEix | F1: PROMETHEUS | G1: REMIND | H1: TIAM-ECN | I1: WITCH | J1: Max points
A2: Storage representation | B2: ='SRF-detailed'!E99 -> 9.75 | C2: ='SRF-detailed'!F99 -> 6.25 | D2: ='SRF-detailed'!G99 -> 5 | E2: ='SRF-detailed'!H99 -> 10 | F2: ='SRF-detailed'!I99 -> 8.25 | G2: ='SRF-detailed'!J99 -> 7.25 | H2: ='SRF-detailed'!K99 -> 0 | I2: ='SRF-detailed'!L99 -> 6 | J2: ='SRF-detailed'!M99 -> 18.5
A3: VRE modelling | B3: ='SRF-detailed'!E155 -> 5.5 | C3: ='SRF-detailed'!F155 -> 4 | D3: ='SRF-detailed'!G155 -> 6.75 | E3: ='SRF-detailed'!H155 -> 6.75 | F3: ='SRF-detailed'!I155 -> 4 | G3: ='SRF-detailed'!J155 -> 6.25 | H3: ='SRF-detailed'!K155 -> 5 | I3: ='SRF-detailed'!L155 -> 3.5 | J3: ='SRF-detailed'!M155 -> 10.5
A4: Temporal representation | B4: ='SRF-detailed'!E161 -> 2 | C4: ='SRF-detailed'!F161 -> 0 | D4: ='SRF-detailed'!G161 -> 4 | E4: ='SRF-detailed'!H161 -> 0 | F4: ='SRF-detailed'!I161 -> 0 | G4: ='SRF-detailed'!J161 -> 0 | H4: ='SRF-detailed'!K161 -> 1 | I4: ='SRF-detailed'!L161 -> 0 | J4: ='SRF-detailed'!M161 -> 6
A5: Spatial representation | B5: ='SRF-detailed'!E167 -> 1 | C5: ='SRF-detailed'!F167 -> 1 | D5: ='SRF-detailed'!G167 -> 1.5 | E5: ='SRF-detailed'!H167 -> 1.5 | F5: ='SRF-detailed'!I167 -> 1 | G5: ='SRF-detailed'!J167 -> 2.5 | H5: ='SRF-detailed'!K167 -> 1.5 | I5: ='SRF-detailed'!L167 -> 0 | J5: ='SRF-detailed'!M167 -> 8

Sheet Figure-2
A1: Category | B1: Indicator | C1: AIM | D1: GCAM | E1: IMAGE | F1: MESSAGEix-GLOBIOM | G1: PROMETHEUS | H1: REMIND | I1: TIAM-ECN | J1: WITCH | K1: Count | L1: Notes
A2: Techno-economic | B2: Electrochemical batteries modelled | C2: 1 | D2: 0 | E2: 0 | F2: 0 | G2: 0 | H2: 1 | I2: 0 | J2: 1 | K2: =SUM(C2:J2) -> 3 | L2: GCAM: generic, parameterised as Li-ion battery; IMAGE: has flow battery
A3: Techno-economic | B3: Storage cost plays a role | C3: 1 | D3: 1 | E3: 0 | F3: 1 | G3: 1 | H3: 1 | I3: 0 | J3: 1 | K3: =SUM(C3:J3) -> 6
A4: Techno-economic | B4: Storage efficiency plays a role | C4: 1 | D4: 1 | E4: 0 | F4: 1 | G4: 0 | H4: 1 | I4: 0 | J4: 0 | K4: =SUM(C4:J4) -> 4
A5: Techno-economic | B5: Storage duration is modelled | C5: 1 | D5: 0 | E5: 0 | F5: 0 | G5: 0 | H5: 0 | I5: 0 | J5: 0 | K5: =SUM(C5:J5) -> 1
A6: Techno-economic | B6: Storage degradation over time modelled | C6: 0 | D6: 0 | E6: 0 | F6: 0 | G6: 0 | H6: 0 | I6: 0 | J6: 0 | K6: =SUM(C6:J6) -> 0
A7: Applications and services | B7: Storage reduces VRE curtailment | C7: 1 | D7: 1 | E7: 1 | F7: 1 | G7: 1 | H7: 1 | I7: 1 | J7: 0 | K7: =SUM(C7:J7) -> 7
A8: Applications and services | B8: Storage for energy services | C8: 1 | D8: 0 | E8: 1 | F8: 1 | G8: 1 | H8: 0 | I8: 0 | J8: 0 | K8: =SUM(C8:J8) -> 4
A9: Applications and services | B9: Storage for power capacity services | C9: 1 | D9: 0 | E9: 1 | F9: 1 | G9: 0 | H9: 0 | I9: 0 | J9: 1 | K9: =SUM(C9:J9) -> 4
A10: Applications and services | B10: Storage for T&D services | C10: 0 | D10: 0 | E10: 1 | F10: 1 | G10: 0 | H10: 0 | I10: 0 | J10: 0 | K10: =SUM(C10:J10) -> 2
A11: Applications and services | B11: Storage multi-service allowed | C11: 1 | D11: 0 | E11: 1 | F11: 0 | G11: 0 | H11: 0 | I11: 0 | J11: 0 | K11: =SUM(C11:J11) -> 2
A12: Integration constraints | B12: Storage parameters vary by scenario | C12: 0 | D12: 1 | E12: 1 | F12: 0 | G12: 1 | H12: 1 | I12: 0 | J12: 0 | K12: =SUM(C12:J12) -> 4
A13: Integration constraints | B13: Storage is not hard-linked to VRE deployment | C13: 1 | D13: 0 | E13: 1 | F13: 1 | G13: 0 | H13: 0 | I13: 0 | J13: 0 | K13: =SUM(C13:J13) -> 3 | L13: IMAGE: The RLDC dataset we use includes required storage capacity for different shares of VRE;
A14: Integration constraints | B14: Storage competes with other flexibility options | C14: 1 | D14: 0 | E14: 1 | F14: 1 | G14: 0 | H14: 0 | I14: 0 | J14: 0 | K14: =SUM(C14:J14) -> 3
A15: Integration constraints | B15: Storage needed to firm VRE-based electricity | C15: 0 | D15: 1 | E15: 0 | F15: 1 | G15: 1 | H15: 1 | I15: 0 | J15: 0 | K15: =SUM(C15:J15) -> 4
A16: Integration constraints | B16: Utility vs. behind-the-meter storage distinguished | C16: 0 | D16: 0 | E16: 0 | F16: 0 | G16: 0 | H16: 0 | I16: 0 | J16: 0 | K16: =SUM(C16:J16) -> 0

Sheet Figure-3
A1: Dimension | B1: Criterion | C1: AIM-T | D1: GCAM | E1: IMAGE | F1: MESSAGEix | G1: PROMETHEUS | H1: REMIND | I1: TIAM-ECN | J1: WITCH | K1: Max points
A2: Explicit storage representation | B2: Storage technology | C2: ='SRF-detailed'!E170 -> 3 | D2: ='SRF-detailed'!F170 -> 2.25 | E2: ='SRF-detailed'!G170 -> 2 | F2: ='SRF-detailed'!H170 -> 2.75 | G2: ='SRF-detailed'!I170 -> 2.75 | H2: ='SRF-detailed'!J170 -> 2.5 | I2: ='SRF-detailed'!K170 -> 0 | J2: ='SRF-detailed'!L170 -> 2.75 | K2: ='SRF-detailed'!M170 -> 4.25
A3: Explicit storage representation | B3: Storage parameters | C3: ='SRF-detailed'!E171 -> 1.75 | D3: ='SRF-detailed'!F171 -> 1.75 | E3: ='SRF-detailed'!G171 -> 0.5 | F3: ='SRF-detailed'!H171 -> 1.75 | G3: ='SRF-detailed'!I171 -> 2 | H3: ='SRF-detailed'!J171 -> 2 | I3: ='SRF-detailed'!K171 -> 0 | J3: ='SRF-detailed'!L171 -> 1 | K3: ='SRF-detailed'!M171 -> 5
A4: Explicit storage representation | B4: Storage services | C4: ='SRF-detailed'!E172 -> 2.75 | D4: ='SRF-detailed'!F172 -> 1 | E4: ='SRF-detailed'!G172 -> 1.5 | F4: ='SRF-detailed'!H172 -> 3.25 | G4: ='SRF-detailed'!I172 -> 1.5 | H4: ='SRF-detailed'!J172 -> 0.75 | I4: ='SRF-detailed'!K172 -> 0 | J4: ='SRF-detailed'!L172 -> 1.25 | K4: ='SRF-detailed'!M172 -> 5.25
A5: Explicit storage representation | B5: Storage integration | C5: ='SRF-detailed'!E173 -> 2.25 | D5: ='SRF-detailed'!F173 -> 1.25 | E5: ='SRF-detailed'!G173 -> 1 | F5: ='SRF-detailed'!H173 -> 2.25 | G5: ='SRF-detailed'!I173 -> 2 | H5: ='SRF-detailed'!J173 -> 2 | I5: ='SRF-detailed'!K173 -> 0 | J5: ='SRF-detailed'!L173 -> 1 | K5: ='SRF-detailed'!M173 -> 4
A6: Explicit storage representation | B6: Subtotal | C6: =SUM(C2:C5) -> 9.75 | D6: =SUM(D2:D5) -> 6.25 | E6: =SUM(E2:E5) -> 5 | F6: =SUM(F2:F5) -> 10 | G6: =SUM(G2:G5) -> 8.25 | H6: =SUM(H2:H5) -> 7.25 | I6: =SUM(I2:I5) -> 0 | J6: =SUM(J2:J5) -> 6 | K6: =SUM(K2:K5) -> 18.5
A7: Breadth in VRE modelling | B7: VRE technology | C7: ='SRF-detailed'!E175 -> 1.25 | D7: ='SRF-detailed'!F175 -> 1 | E7: ='SRF-detailed'!G175 -> 1.75 | F7: ='SRF-detailed'!H175 -> 1 | G7: ='SRF-detailed'!I175 -> 1 | H7: ='SRF-detailed'!J175 -> 1.25 | I7: ='SRF-detailed'!K175 -> 1.25 | J7: ='SRF-detailed'!L175 -> 1 | K7: ='SRF-detailed'!M175 -> 1.75
A8: Breadth in VRE modelling | B8: VRE parameters | C8: ='SRF-detailed'!E176 -> 1.5 | D8: ='SRF-detailed'!F176 -> 1 | E8: ='SRF-detailed'!G176 -> 1.75 | F8: ='SRF-detailed'!H176 -> 1.5 | G8: ='SRF-detailed'!I176 -> 1.25 | H8: ='SRF-detailed'!J176 -> 1.25 | I8: ='SRF-detailed'!K176 -> 1.25 | J8: ='SRF-detailed'!L176 -> 1.25 | K8: ='SRF-detailed'!M176 -> 2
A9: Breadth in VRE modelling | B9: VRE integration | C9: ='SRF-detailed'!E177 -> 1.25 | D9: ='SRF-detailed'!F177 -> 1.5 | E9: ='SRF-detailed'!G177 -> 1.75 | F9: ='SRF-detailed'!H177 -> 2.5 | G9: ='SRF-detailed'!I177 -> 1.25 | H9: ='SRF-detailed'!J177 -> 2.25 | I9: ='SRF-detailed'!K177 -> 1 | J9: ='SRF-detailed'!L177 -> 0.5 | K9: ='SRF-detailed'!M177 -> 3.25
A10: Breadth in VRE modelling | B10: Flexibility portfolio | C10: ='SRF-detailed'!E178 -> 1.5 | D10: ='SRF-detailed'!F178 -> 0.5 | E10: ='SRF-detailed'!G178 -> 1.5 | F10: ='SRF-detailed'!H178 -> 1.75 | G10: ='SRF-detailed'!I178 -> 0.5 | H10: ='SRF-detailed'!J178 -> 1.5 | I10: ='SRF-detailed'!K178 -> 1.5 | J10: ='SRF-detailed'!L178 -> 0.75 | K10: ='SRF-detailed'!M178 -> 3.5
A11: Breadth in VRE modelling | B11: Subtotal | C11: =SUM(C7:C10) -> 5.5 | D11: =SUM(D7:D10) -> 4 | E11: =SUM(E7:E10) -> 6.75 | F11: =SUM(F7:F10) -> 6.75 | G11: =SUM(G7:G10) -> 4 | H11: =SUM(H7:H10) -> 6.25 | I11: =SUM(I7:I10) -> 5 | J11: =SUM(J7:J10) -> 3.5 | K11: =SUM(K7:K10) -> 10.5
A12: Temporal representation | B12: Temporal resolution | C12: ='SRF-detailed'!E180 -> 2 | D12: ='SRF-detailed'!F180 -> 0 | E12: ='SRF-detailed'!G180 -> 3 | F12: ='SRF-detailed'!H180 -> 0 | G12: ='SRF-detailed'!I180 -> 0 | H12: ='SRF-detailed'!J180 -> 0 | I12: ='SRF-detailed'!K180 -> 1 | J12: ='SRF-detailed'!L180 -> 0 | K12: ='SRF-detailed'!M180 -> 4
A13: Temporal representation | B13: Temporal modelling | C13: ='SRF-detailed'!E181 -> 0 | D13: ='SRF-detailed'!F181 -> 0 | E13: ='SRF-detailed'!G181 -> 1 | F13: ='SRF-detailed'!H181 -> 0 | G13: ='SRF-detailed'!I181 -> 0 | H13: ='SRF-detailed'!J181 -> 0 | I13: ='SRF-detailed'!K181 -> 0 | J13: ='SRF-detailed'!L181 -> 0 | K13: ='SRF-detailed'!M181 -> 2
A14: Temporal representation | B14: Subtotal | C14: =SUM(C12:C13) -> 2 | D14: =SUM(D12:D13) -> 0 | E14: =SUM(E12:E13) -> 4 | F14: =SUM(F12:F13) -> 0 | G14: =SUM(G12:G13) -> 0 | H14: =SUM(H12:H13) -> 0 | I14: =SUM(I12:I13) -> 1 | J14: =SUM(J12:J13) -> 0 | K14: =SUM(K12:K13) -> 6
A15: Spatial structure | B15: Spatial resolution | C15: ='SRF-detailed'!E183 -> 1 | D15: ='SRF-detailed'!F183 -> 1 | E15: ='SRF-detailed'!G183 -> 1 | F15: ='SRF-detailed'!H183 -> 1 | G15: ='SRF-detailed'!I183 -> 1 | H15: ='SRF-detailed'!J183 -> 2 | I15: ='SRF-detailed'!K183 -> 1 | J15: ='SRF-detailed'!L183 -> 0 | K15: ='SRF-detailed'!M183 -> 4
A16: Spatial structure | B16: Grid representation | C16: ='SRF-detailed'!E184 -> 0 | D16: ='SRF-detailed'!F184 -> 0 | E16: ='SRF-detailed'!G184 -> 0.5 | F16: ='SRF-detailed'!H184 -> 0.5 | G16: ='SRF-detailed'!I184 -> 0 | H16: ='SRF-detailed'!J184 -> 0.5 | I16: ='SRF-detailed'!K184 -> 0.5 | J16: ='SRF-detailed'!L184 -> 0 | K16: ='SRF-detailed'!M184 -> 4
A17: Spatial structure | B17: Subtotal | C17: =SUM(C15:C16) -> 1 | D17: =SUM(D15:D16) -> 1 | E17: =SUM(E15:E16) -> 1.5 | F17: =SUM(F15:F16) -> 1.5 | G17: =SUM(G15:G16) -> 1 | H17: =SUM(H15:H16) -> 2.5 | I17: =SUM(I15:I16) -> 1.5 | J17: =SUM(J15:J16) -> 0 | K17: =SUM(K15:K16) -> 8

Sheet Sheet2
A1: Category | B1: Indicator | C1: Number of models
A2: Techno-economic | B2: Electrochemical batteries modelled | C2: 3
A3: Techno-economic | B3: Storage cost plays a role | C3: 5
A4: Techno-economic | B4: Storage efficiency plays a role | C4: 4
A5: Techno-economic | B5: Storage duration is modelled | C5: 1
A6: Techno-economic | B6: Storage degradation over time modelled | C6: 0
A7: Services | B7: Storage reduces VRE curtailment | C7: 7
A8: Services | B8: Storage for energy services | C8: 4
A9: Services | B9: Storage for power capacity services | C9: 4
A10: Services | B10: Storage for T&D services | C10: 2
A11: Services | B11: Storage multi-service allowed | C11: 2
A12: Modelling constraints | B12: Storage parameters vary by scenario | C12: 4
A13: Modelling constraints | B13: Storage is not hard-linked to VRE deployment | C13: 3
... A16: Modelling constraints | B16: Utility vs. behind-the-meter storage distinguished | C16: 0
